{"authorDailyContributionsMap":{"Kokseng1":[{"date":"2023-09-25","commitResults":[{"hash":"5aa5a7ca0a8a9c04346b7c4295c35d063a7114bd","isMergeCommit":false,"messageTitle":"Update AboutUs.md. Add kokseng1.png and kokseng1.md","messageBody":"","fileTypesAndContributionMap":{"docs":{"insertions":31,"deletions":5}}},{"hash":"7366af756b3845b4e1527773d13136efbbbec4f0","isMergeCommit":false,"messageTitle":"Update UserGuide.md. Add Uimockup.png","messageBody":"","fileTypesAndContributionMap":{"docs":{"insertions":6,"deletions":2}}},{"hash":"44deeae6c5436ae631ebf530cf0fefcf6fb1b690","isMergeCommit":false,"messageTitle":"Update UserGuide.md. Add Uimockup.png","messageBody":"","fileTypesAndContributionMap":{"docs":{"insertions":1,"deletions":1}}},{"hash":"56337199c6dc53790c3697d88bd517e8813ba9cc","isMergeCommit":false,"messageTitle":"Update UserGuide.md. Add Uimockup.png","messageBody":"","fileTypesAndContributionMap":{"docs":{"insertions":1,"deletions":1}}},{"hash":"2c93db4167746d17ac4cf1e67ad9ef666d763f68","isMergeCommit":true,"messageTitle":"Merge pull request #32 from vansh284/documentation-11-UpdateAboutUs","messageBody":"Update AboutUs and add skeletal PPP","fileTypesAndContributionMap":{}}]},{"date":"2023-09-26","commitResults":[{"hash":"3557aff181e8e0ec0d9587b003bd22009844a65d","isMergeCommit":false,"messageTitle":"Update DeveloperGuide.md to include add use case","messageBody":"","fileTypesAndContributionMap":{"docs":{"insertions":25,"deletions":4}}},{"hash":"2e3bfdd394bdd5b9a3fdaa772e21a9babb2836c1","isMergeCommit":false,"messageTitle":"Update DeveloperGuide.md to include add use case","messageBody":"","fileTypesAndContributionMap":{"docs":{"insertions":1,"deletions":1}}}]},{"date":"2023-09-28","commitResults":[{"hash":"78cd65af3708352cbbf45157ababea3ed965c246","isMergeCommit":false,"messageTitle":"Update DeveloperGuide.md","messageBody":"Corrected mistakes brought up in Gavin and Vansh\u0027s comments","fileTypesAndContributionMap":{"docs":{"insertions":8,"deletions":8}}},{"hash":"8ea8e72a8a9c720defb173753b256acc3644f599","isMergeCommit":true,"messageTitle":"Merge pull request #42 from alvinlim277/documentation-34-UpdateDeveloperGuide","messageBody":"Add \u0027exit program\u0027 use case in Developer Guide","fileTypesAndContributionMap":{}}]},{"date":"2023-10-01","commitResults":[{"hash":"5ff1ecc8d3651dcb7136a44eb9435f7193db644e","isMergeCommit":false,"messageTitle":"Update DeveloperGuide.md to include patient management user stories","messageBody":"","fileTypesAndContributionMap":{"docs":{"insertions":19,"deletions":13}}},{"hash":"edd1860c018a202a6552663c4cadfb4355c81a9c","isMergeCommit":false,"messageTitle":"Update DeveloperGuide.md to include patient management user stories","messageBody":"","fileTypesAndContributionMap":{"docs":{"insertions":19,"deletions":8}}},{"hash":"f84c1f1e48ec2e8621f5bf624fc92e4870d736f9","isMergeCommit":true,"messageTitle":"merge changes from remote","messageBody":"","fileTypesAndContributionMap":{}},{"hash":"5e912fc0e3adfcb0088b70f16e3d0ff2803e9e7b","isMergeCommit":false,"messageTitle":"add patient management user stories to DeveloperGuide.md","messageBody":"","fileTypesAndContributionMap":{"docs":{"insertions":19,"deletions":13}}}]},{"date":"2023-10-09","commitResults":[{"hash":"f685e634889d4c3c4bee22dd1f67b48c503f8c9f","isMergeCommit":true,"messageTitle":"merge","messageBody":"","fileTypesAndContributionMap":{}}]},{"date":"2023-10-10","commitResults":[{"hash":"adb10800385b94a08871b67f605b21ff3cbadfe3","isMergeCommit":false,"messageTitle":"Add \"Specialty\" field for specialists. Wherever a Specialist object is present, it should have a non null Specialty field. Users can now add or edit any specialist\u0027s specialty.","messageBody":"","fileTypesAndContributionMap":{"functional-code":{"insertions":202,"deletions":74},"test-code":{"insertions":77,"deletions":74}}},{"hash":"4888d10b2921cf0ddeb5df9b92f095f1f5689862","isMergeCommit":false,"messageTitle":"resolved checkstyle issue","messageBody":"","fileTypesAndContributionMap":{"functional-code":{"insertions":108,"deletions":41},"test-code":{"insertions":44,"deletions":4}}},{"hash":"1c89b2b0fbe6b09103ee05b94645025acce7c202","isMergeCommit":false,"messageTitle":"resolved more checkstyle issue","messageBody":"","fileTypesAndContributionMap":{"test-code":{"insertions":47,"deletions":25}}},{"hash":"6844a9819cf217b337c4832ddfc3881cb3e9c553","isMergeCommit":false,"messageTitle":"update tests to meet codecov","messageBody":"","fileTypesAndContributionMap":{"test-code":{"insertions":97,"deletions":9}}}]},{"date":"2023-10-12","commitResults":[{"hash":"fc3382d7d06d1ebd71d7787e95b61be55e408eae","isMergeCommit":false,"messageTitle":"updated toString methods to be less repetitive","messageBody":"","fileTypesAndContributionMap":{"functional-code":{"insertions":21,"deletions":17}}},{"hash":"63c9c32602126196fd24f37632acc7ca6911a629","isMergeCommit":false,"messageTitle":"Update StringUtil.java","messageBody":"corrected javadoc","fileTypesAndContributionMap":{"functional-code":{"insertions":1,"deletions":1}}}]},{"date":"2023-10-16","commitResults":[{"hash":"975ff79008266862f7a4f0d4b6c960fb60b90d1f","isMergeCommit":false,"messageTitle":"Update error messages","messageBody":"","fileTypesAndContributionMap":{"functional-code":{"insertions":140,"deletions":67},"test-code":{"insertions":25,"deletions":18}}}]},{"date":"2023-10-17","commitResults":[{"hash":"eab88efcb395dd6f258431c8473f44ff789c82cd","isMergeCommit":true,"messageTitle":"Merge branch \u0027master\u0027 into feature-65-ErrorMessages","messageBody":"","fileTypesAndContributionMap":{}},{"hash":"3502d864bae56f5bd78819e16f636606427a0509","isMergeCommit":false,"messageTitle":"conflict management","messageBody":"","fileTypesAndContributionMap":{"functional-code":{"insertions":8,"deletions":12},"test-code":{"insertions":7,"deletions":7}}},{"hash":"c3193d1246c24c006ac8659776734d34ae1a2bf3","isMergeCommit":false,"messageTitle":"add test","messageBody":"","fileTypesAndContributionMap":{"test-code":{"insertions":2,"deletions":0}}},{"hash":"cd89326acb51d05da40c5512be8d1ce62b0af596","isMergeCommit":false,"messageTitle":"change unused strings in add, edit and find to private","messageBody":"","fileTypesAndContributionMap":{"functional-code":{"insertions":11,"deletions":13}}},{"hash":"3c0ab12dae402a2b2e90ef37deec809187dc0c8b","isMergeCommit":true,"messageTitle":"Merge pull request #76 from angkyakdifp/branch-med-history-2","messageBody":"Enable Medical History to be optional and Multiple value","fileTypesAndContributionMap":{}},{"hash":"49022a819f7f87e5a4b74c3efb8e0b8a4a963520","isMergeCommit":true,"messageTitle":"Merge branch \u0027master\u0027 into feature-65-ErrorMessages","messageBody":"","fileTypesAndContributionMap":{}},{"hash":"2ec942fb2eea556cdc7eb17579304f8b03184d6a","isMergeCommit":false,"messageTitle":"merge conflict","messageBody":"","fileTypesAndContributionMap":{"test-code":{"insertions":2,"deletions":0}}},{"hash":"11b6740f64151c1c6e19bf5245487dd87af93380","isMergeCommit":false,"messageTitle":"checkstyle","messageBody":"","fileTypesAndContributionMap":{"test-code":{"insertions":1,"deletions":1}}}]},{"date":"2023-10-25","commitResults":[{"hash":"9a335ffbd685b2a6bc9a91d57ef32dd2c795f1b3","isMergeCommit":false,"messageTitle":"add undo/redo function todo in future commits : resolve test, add more tests","messageBody":"","fileTypesAndContributionMap":{"functional-code":{"insertions":315,"deletions":20},"test-code":{"insertions":145,"deletions":37}}},{"hash":"4cef169dbffff87560b98ef7628570bb53d86bed","isMergeCommit":true,"messageTitle":"Merge https://github.com/AY2324S1-CS2103T-W13-1/tp into feature-86-UndoRedo","messageBody":"","fileTypesAndContributionMap":{}},{"hash":"d66660754032a776a5de53622009037ad97e04e2","isMergeCommit":true,"messageTitle":"merge main, took out undo test","messageBody":"","fileTypesAndContributionMap":{}},{"hash":"1f6665bd3f37ce814c9628301e89f8bd5314ae54","isMergeCommit":true,"messageTitle":"Merge https://github.com/AY2324S1-CS2103T-W13-1/tp into feature-86-UndoRedo","messageBody":"","fileTypesAndContributionMap":{}},{"hash":"8d3ebec391b187826ca8a4b64d02ca0641f61ead","isMergeCommit":true,"messageTitle":"gerge branch \u0027feature-86-UndoRedo\u0027 of https://github.com/Kokseng1/tp into feature-86-UndoRedo merge head","messageBody":"src/test/java/seedu/address/logic/commands/DeleteCommandTest.java\n","fileTypesAndContributionMap":{}},{"hash":"40f275cc7deaf5fa61a5c4a042c98e71cb77f21d","isMergeCommit":false,"messageTitle":"Update user guide to include undo redo feature","messageBody":"","fileTypesAndContributionMap":{"docs":{"insertions":14,"deletions":0}}}]},{"date":"2023-10-26","commitResults":[{"hash":"ba18ef36acae36d6f1656434c33c7cb8542f81a6","isMergeCommit":true,"messageTitle":"Merge pull request #90 from vansh284/story-85-RepeatCommand","messageBody":"Recall Recent Commands Feature","fileTypesAndContributionMap":{}},{"hash":"c1456ad081769d50460b6f3301f0d4d87158720d","isMergeCommit":true,"messageTitle":"merge recall last command","messageBody":"","fileTypesAndContributionMap":{}},{"hash":"8ffef8469a004a4ae333b6a4ad2f21a5c112449e","isMergeCommit":false,"messageTitle":"Fix spelling error in UG, update Undo/Redo","messageBody":"","fileTypesAndContributionMap":{"functional-code":{"insertions":1,"deletions":3},"docs":{"insertions":1,"deletions":1}}},{"hash":"17c76f08fd3bc7f41e98cafb6f1fc7803250d03e","isMergeCommit":false,"messageTitle":"update Redo","messageBody":"","fileTypesAndContributionMap":{"functional-code":{"insertions":1,"deletions":3}}}]},{"date":"2023-10-31","commitResults":[{"hash":"292e0a4f28cc05aecdf4107ee87b949b517eddb0","isMergeCommit":false,"messageTitle":"update Undo/Redo to include addsc","messageBody":"","fileTypesAndContributionMap":{"functional-code":{"insertions":83,"deletions":97},"test-code":{"insertions":419,"deletions":81}}},{"hash":"0adc5bfac3f8565117acc674005c21c958ad98e6","isMergeCommit":true,"messageTitle":"merge conflict","messageBody":"","fileTypesAndContributionMap":{}},{"hash":"98b0e5ae428b864119540c39455311d546742bf4","isMergeCommit":true,"messageTitle":"Merge pull request #111 from vansh284/feature-7-customColorSchemes","messageBody":"Add custom color schemes (light theme and dark theme)","fileTypesAndContributionMap":{}},{"hash":"37f32912b1e0d886a2e0b5d65d88041289cfe169","isMergeCommit":true,"messageTitle":"Merge https://github.com/AY2324S1-CS2103T-W13-1/tp into bugFix-107-UndoRedo","messageBody":"","fileTypesAndContributionMap":{}},{"hash":"ed2774fb19bba979d81191337da5b9b4216fe38d","isMergeCommit":false,"messageTitle":"Merge themecommand, add more testcoverage in undo redo test","messageBody":"","fileTypesAndContributionMap":{"functional-code":{"insertions":1,"deletions":1},"test-code":{"insertions":138,"deletions":77}}},{"hash":"aeacac64aa5cb2e928fa798692d1148f5b85db6d","isMergeCommit":false,"messageTitle":"update DG to reflect current undo/redo implementation","messageBody":"","fileTypesAndContributionMap":{"docs":{"insertions":8,"deletions":23}}}]},{"date":"2023-11-02","commitResults":[{"hash":"a1da5c3bcfa8fa04171facead93bbbb3827c6be0","isMergeCommit":true,"messageTitle":"Merge https://github.com/AY2324S1-CS2103T-W13-1/tp into bugFix-107-UndoRedo","messageBody":"","fileTypesAndContributionMap":{}},{"hash":"f46c8489ab2e4b0a2bdffe023be2c5d7bc5329a5","isMergeCommit":false,"messageTitle":"Removed irrelevant comment","messageBody":"","fileTypesAndContributionMap":{"functional-code":{"insertions":0,"deletions":1}}}]},{"date":"2023-11-06","commitResults":[{"hash":"c0973260ce00943c055f741c15c4c7703ca35c70","isMergeCommit":false,"messageTitle":"Move tracking job from addressbook to modelmanager","messageBody":"","fileTypesAndContributionMap":{"functional-code":{"insertions":213,"deletions":179},"test-code":{"insertions":66,"deletions":81}}},{"hash":"1d15039020ab6779ac7bc12b1bb94d46d6d29bb1","isMergeCommit":false,"messageTitle":"TODO : sort out filteredPerson in ModelManager after Undo command","messageBody":"","fileTypesAndContributionMap":{"functional-code":{"insertions":19,"deletions":9},"test-code":{"insertions":22,"deletions":0}}},{"hash":"420440ed180119165725af38176f61db83416fa1","isMergeCommit":false,"messageTitle":"TODO : sort out filteredPerson in ModelManager after Undo command","messageBody":"","fileTypesAndContributionMap":{"functional-code":{"insertions":1,"deletions":0},"test-code":{"insertions":23,"deletions":22}}}]},{"date":"2023-11-07","commitResults":[{"hash":"18a3c24a533b7ea72db3014b97fcc37d08efba39","isMergeCommit":false,"messageTitle":"Fix undo/redo integration bug. Update UG and DG for undo feature","messageBody":"","fileTypesAndContributionMap":{"functional-code":{"insertions":18,"deletions":11},"docs":{"insertions":53,"deletions":75},"test-code":{"insertions":0,"deletions":23}}},{"hash":"1d21092f46f700e636420fd15534c4cb1fc553cd","isMergeCommit":false,"messageTitle":"Checkstyle","messageBody":"","fileTypesAndContributionMap":{"functional-code":{"insertions":1,"deletions":3},"test-code":{"insertions":0,"deletions":1}}},{"hash":"e6373edb0f15cf24f65e8b1522222eb313f45aa4","isMergeCommit":false,"messageTitle":"spelling error","messageBody":"","fileTypesAndContributionMap":{"docs":{"insertions":2,"deletions":2}}},{"hash":"ea9b787b744a5196f43ebde8d47e0194ec65932e","isMergeCommit":false,"messageTitle":"fix specialist tag undo bug","messageBody":"","fileTypesAndContributionMap":{"functional-code":{"insertions":1,"deletions":1},"test-code":{"insertions":1,"deletions":1}}},{"hash":"5e62ea2721bf89ad52b9a0d08aa496139531d12e","isMergeCommit":false,"messageTitle":"Add comment to justify typecast in ModelManager","messageBody":"","fileTypesAndContributionMap":{"functional-code":{"insertions":7,"deletions":5}}}]},{"date":"2023-11-08","commitResults":[{"hash":"87782c04cf7a7963b1f0922a6713f198fbf79928","isMergeCommit":false,"messageTitle":"Make undo in UG clearer","messageBody":"","fileTypesAndContributionMap":{"docs":{"insertions":1,"deletions":1}}}]},{"date":"2023-11-11","commitResults":[{"hash":"0c11734455ca2e4119a6458833359ee4cb407d33","isMergeCommit":false,"messageTitle":"Fix resetData bug in ModelManager.java Update documentation","messageBody":"","fileTypesAndContributionMap":{"functional-code":{"insertions":8,"deletions":7},"docs":{"insertions":28,"deletions":19}}}]},{"date":"2023-11-12","commitResults":[{"hash":"c51eb2640829dbbb67933aa5f58bbd80fe5f3bf2","isMergeCommit":false,"messageTitle":"UndoSequenceDiagram","messageBody":"","fileTypesAndContributionMap":{"docs":{"insertions":1,"deletions":1}}},{"hash":"8a0b72662ed81d50d2f7526d04bb4549d6fd3550","isMergeCommit":false,"messageTitle":"Enter button emphasis in UG","messageBody":"","fileTypesAndContributionMap":{"docs":{"insertions":1,"deletions":1}}},{"hash":"0b9c48006a5e44aa02123e73a5be0cacaa05b804","isMergeCommit":true,"messageTitle":"Merge branch \u0027AY2324S1-CS2103T-W13-1:master\u0027 into bugfix-documentation","messageBody":"","fileTypesAndContributionMap":{}}]}],"vansh284":[{"date":"2023-09-25","commitResults":[{"hash":"d97740beb4d0b14be685f1a744ec53559f98340c","isMergeCommit":false,"messageTitle":"Update AboutUs","messageBody":"","fileTypesAndContributionMap":{"docs":{"insertions":6,"deletions":6}}},{"hash":"58891d6677bc5243754a43f4e2f74afa04ac3c1e","isMergeCommit":false,"messageTitle":"Add skeletal PPP","messageBody":"","fileTypesAndContributionMap":{"docs":{"insertions":23,"deletions":0}}},{"hash":"7165a173e342e4a6f291976425aacd8e7205184c","isMergeCommit":true,"messageTitle":"Merge pull request #30 from Kokseng1/documentation-18-UpdateUserGuide","messageBody":"Update UserGuide.md. and add Uimockup.png","fileTypesAndContributionMap":{}}]},{"date":"2023-09-26","commitResults":[{"hash":"22ab15fd6210c06c026b8666d6f470192d7c6331","isMergeCommit":false,"messageTitle":"Update user guide delete command","messageBody":"","fileTypesAndContributionMap":{"docs":{"insertions":23,"deletions":43}}},{"hash":"950409b4ccae5abf0853786479a53ab05e4729d4","isMergeCommit":false,"messageTitle":"Add NFRs, target user profile and value proposition","messageBody":"","fileTypesAndContributionMap":{"docs":{"insertions":41,"deletions":22}}}]},{"date":"2023-09-27","commitResults":[{"hash":"8b47cafbf2239aecc6d41c5db4d5ada5aee3211b","isMergeCommit":false,"messageTitle":"Rectify grammatical error","messageBody":"","fileTypesAndContributionMap":{"docs":{"insertions":1,"deletions":1}}},{"hash":"10d8b1a2bad6944fef0d70dbd62cc2f6a91ed82d","isMergeCommit":false,"messageTitle":"Rectify grammatical errors","messageBody":"","fileTypesAndContributionMap":{"docs":{"insertions":2,"deletions":2}}},{"hash":"9e62bd58ea11f5d630f5defac0f4ee64908d0687","isMergeCommit":true,"messageTitle":"Merge pull request #39 from alvinlim277/documentation-18-UserGuide","messageBody":"","fileTypesAndContributionMap":{}},{"hash":"318f82ea2b323af572e86276cce42e129f7de5a2","isMergeCommit":true,"messageTitle":"Merge pull request #35 from vansh284/documentation-18-UpdateDeleteCommand","messageBody":"","fileTypesAndContributionMap":{}},{"hash":"92354751a60e1a0d480610f7c4f8426c97f10676","isMergeCommit":true,"messageTitle":"Merge pull request #36 from vansh284/documentation-34-nfr","messageBody":"","fileTypesAndContributionMap":{}}]},{"date":"2023-09-29","commitResults":[{"hash":"e664a2463e58fe7c94311e3e66f82f2bf4091aa7","isMergeCommit":false,"messageTitle":"Add some user stories","messageBody":"","fileTypesAndContributionMap":{"docs":{"insertions":10,"deletions":10}}},{"hash":"2ed61efff239dbd0e80ddfa8fb4397de28d46199","isMergeCommit":true,"messageTitle":"Merge pull request #44 from Gavino3o/documentation-34-AddUserStories","messageBody":"Add Customization and Shortcut User Stories","fileTypesAndContributionMap":{}},{"hash":"06fb05f348e4630dbed6ccc67b92f4efb3951e05","isMergeCommit":true,"messageTitle":"Make minor changes","messageBody":"","fileTypesAndContributionMap":{}}]},{"date":"2023-10-02","commitResults":[{"hash":"0699c1b1f1b75857f82ce8b1bbe6263ae3321d9e","isMergeCommit":true,"messageTitle":"Merge pull request #46 from alvinlim277/documentation-34-UpdateDeveloperGuide","messageBody":"Add data management User Stories to Developer Guide","fileTypesAndContributionMap":{}}]},{"date":"2023-10-03","commitResults":[{"hash":"92e8454ce3c2b7f2bcab7e6fc194d666f4425b96","isMergeCommit":true,"messageTitle":"Merge pull request #47 from alvinlim277/documentation-19-UpdateReadMe","messageBody":"Add Ui mockup to README","fileTypesAndContributionMap":{}}]},{"date":"2023-10-05","commitResults":[{"hash":"fe0d6d4d04951613b8623a081ac4ea8912b100f6","isMergeCommit":true,"messageTitle":"Merge pull request #50 from angkyakdifp/master","messageBody":"Edit the Quick Start for the User Guide","fileTypesAndContributionMap":{}},{"hash":"2e5f9fe5deb9f0a059c49952b4da4fb77b81385b","isMergeCommit":true,"messageTitle":"Merge pull request #57 from alvinlim277/documentation-56-UpdateConfig","messageBody":"Update site-wide settings","fileTypesAndContributionMap":{}}]},{"date":"2023-10-06","commitResults":[{"hash":"67293a5bdb4e4021db61c61e60ff052609dfe803","isMergeCommit":false,"messageTitle":"Separate people into patients and specialist","messageBody":"","fileTypesAndContributionMap":{"functional-code":{"insertions":607,"deletions":109},"other":{"insertions":40,"deletions":33},"test-code":{"insertions":567,"deletions":164}}},{"hash":"61146a50c1c8f760e343d89b1c8c4ede89fd0e9f","isMergeCommit":false,"messageTitle":"Add tests to increase coverage","messageBody":"","fileTypesAndContributionMap":{"test-code":{"insertions":106,"deletions":71}}}]},{"date":"2023-10-07","commitResults":[{"hash":"ea1494d0d78455ad4cfaeebafaa7dd5bcaf4b565","isMergeCommit":false,"messageTitle":"Add tests to cover edit command parser","messageBody":"","fileTypesAndContributionMap":{"test-code":{"insertions":1,"deletions":1}}}]},{"date":"2023-10-09","commitResults":[{"hash":"939afeb730a036473899425a2c4f3a0563a85d0c","isMergeCommit":true,"messageTitle":"Merge pull request #58 from vansh284/story-38-PeopleTypes","messageBody":"Deal with patients and specialist records separately in the address book","fileTypesAndContributionMap":{}}]},{"date":"2023-10-12","commitResults":[{"hash":"f249bb1321574386848a4678701b422fdd6f7da9","isMergeCommit":true,"messageTitle":"Merge pull request #60 from Kokseng1/story-54-AddSpecialistFields","messageBody":"Track specialist by specialty","fileTypesAndContributionMap":{}}]},{"date":"2023-10-13","commitResults":[{"hash":"1be617bbf51156c2305ce2c425b0b2ec44ef76d5","isMergeCommit":true,"messageTitle":"Merge pull request #62 from alvinlim277/feature-61-DisplayRecordsSeparately","messageBody":"Display patient and specialist records separately when listing","fileTypesAndContributionMap":{}},{"hash":"44fde4673d8c7c883e825dc1bcba8906b0e3a517","isMergeCommit":true,"messageTitle":"Merge pull request #64 from angkyakdifp/branch-addMedicalHistory","messageBody":"Add medical history field for patient","fileTypesAndContributionMap":{}}]},{"date":"2023-10-15","commitResults":[{"hash":"e32ec5e735ed08f133a62e44eea881ccc5bf51ad","isMergeCommit":false,"messageTitle":"Add age field to patient","messageBody":"","fileTypesAndContributionMap":{"functional-code":{"insertions":166,"deletions":46},"test-code":{"insertions":224,"deletions":62}}}]},{"date":"2023-10-16","commitResults":[{"hash":"a887af64ecd34f878cd4fd459eb7e76f2a150651","isMergeCommit":true,"messageTitle":"Merge branch \u0027master\u0027 of github.com:vansh284/tp into story-37-PatientAge","messageBody":"","fileTypesAndContributionMap":{}},{"hash":"a1c405b302f68d1d43394265c7b52749faf3b1ce","isMergeCommit":false,"messageTitle":"Add predicate to allow finding patient by age","messageBody":"","fileTypesAndContributionMap":{"functional-code":{"insertions":66,"deletions":4}}},{"hash":"53322ce50e5115ff8c6c203980c72f157c33af20","isMergeCommit":false,"messageTitle":"Add tests for parser","messageBody":"","fileTypesAndContributionMap":{"test-code":{"insertions":56,"deletions":5}}},{"hash":"21516fecd8eb78dc14548ac115a6d39c1bfc1e84","isMergeCommit":false,"messageTitle":"Fix error in header comments","messageBody":"","fileTypesAndContributionMap":{"functional-code":{"insertions":2,"deletions":3}}},{"hash":"646455340d15fb1fef475fa3f86517e566479584","isMergeCommit":true,"messageTitle":"Merge pull request #72 from vansh284/story-37-PatientAge","messageBody":"Add age field to patients","fileTypesAndContributionMap":{}},{"hash":"3c19509461357ca01d7e380e7a3a465b50449a30","isMergeCommit":true,"messageTitle":"Merge pull request #73 from alvinlim277/feature-67-LocationField","messageBody":"Change address to location and make it exclusive to specialists","fileTypesAndContributionMap":{}}]},{"date":"2023-10-17","commitResults":[{"hash":"2ec56a4684bb1d0f35b85c909824751a7cf99e17","isMergeCommit":true,"messageTitle":"Merge pull request #75 from Gavino3o/test-71-FindCommandCodeCov","messageBody":"Improve Code Coverage of Find Command","fileTypesAndContributionMap":{}}]},{"date":"2023-10-18","commitResults":[{"hash":"c75845fee715c90ca97d07ee39b3d2c15a42214b","isMergeCommit":true,"messageTitle":"Merge pull request #77 from Kokseng1/feature-65-ErrorMessages","messageBody":"Improve error messages","tags":["v1.2"],"fileTypesAndContributionMap":{}}]},{"date":"2023-10-20","commitResults":[{"hash":"3c1e92fd45d0ed17b7453b9af10520b04649ed5c","isMergeCommit":true,"messageTitle":"Merge pull request #82 from angkyakdifp/master","messageBody":"Fix bug for medical history display.","fileTypesAndContributionMap":{}},{"hash":"1d81005ab03082b504656a4fbab7b7333005db3f","isMergeCommit":false,"messageTitle":"Update version number for trial JAR release","messageBody":"","fileTypesAndContributionMap":{"functional-code":{"insertions":1,"deletions":1}}}]},{"date":"2023-10-21","commitResults":[{"hash":"caac94588a5b79342dcc9ccafd3cab715898d7cf","isMergeCommit":true,"messageTitle":"Merge pull request #81 from Gavino3o/bugfix-78-FindCommandInvalidArgParseError","messageBody":"Fix find command invalid argument parsing","fileTypesAndContributionMap":{}}]},{"date":"2023-10-22","commitResults":[{"hash":"50f223f72a9172b17467ee91fd7f7c155752e442","isMergeCommit":false,"messageTitle":"Enable assertions in gradle","messageBody":"","fileTypesAndContributionMap":{"other":{"insertions":4,"deletions":0}}}]},{"date":"2023-10-24","commitResults":[{"hash":"cf22f2bac359ce2921adf809cc8d1b504a8e0221","isMergeCommit":false,"messageTitle":"Add repeat recent commands feature","messageBody":"","fileTypesAndContributionMap":{"functional-code":{"insertions":178,"deletions":3}}}]},{"date":"2023-10-25","commitResults":[{"hash":"4fc99b52cc2128c47d40c85777a4d94a8f3758ae","isMergeCommit":false,"messageTitle":"Add framework for testing","messageBody":"","fileTypesAndContributionMap":{"functional-code":{"insertions":16,"deletions":0},"test-code":{"insertions":42,"deletions":0}}},{"hash":"77baa6ed5baa0766746f07c7ffe8e3b39bd50604","isMergeCommit":false,"messageTitle":"Add testing for CommandStringStash","messageBody":"","fileTypesAndContributionMap":{"functional-code":{"insertions":49,"deletions":20},"test-code":{"insertions":153,"deletions":7}}},{"hash":"7d7253fab772457e507932cfbced1975907e0278","isMergeCommit":false,"messageTitle":"Update user guide for recalling recent commands","messageBody":"","fileTypesAndContributionMap":{"docs":{"insertions":12,"deletions":0}}}]},{"date":"2023-10-26","commitResults":[{"hash":"625a1dd3343adb4cc4538543a5d803ac19e2fecb","isMergeCommit":false,"messageTitle":"Improve formatting","messageBody":"","fileTypesAndContributionMap":{"functional-code":{"insertions":2,"deletions":1}}},{"hash":"3f3eb2fa74660896ce4943ab31859712cabd4f52","isMergeCommit":false,"messageTitle":"Make code for CommandStringStash simpler","messageBody":"","fileTypesAndContributionMap":{"functional-code":{"insertions":30,"deletions":47},"docs":{"insertions":2,"deletions":2},"test-code":{"insertions":29,"deletions":91}}},{"hash":"d833c1a971b83e9e1c41cf30be84af0adb59e18b","isMergeCommit":false,"messageTitle":"Update developer guide with recall command","messageBody":"","fileTypesAndContributionMap":{"functional-code":{"insertions":2,"deletions":2},"docs":{"insertions":316,"deletions":2}}},{"hash":"2d5201bc19cfa654f7832c732e43ce592ec1d75b","isMergeCommit":false,"messageTitle":"Fix typo in image links in DG","messageBody":"","fileTypesAndContributionMap":{"docs":{"insertions":9,"deletions":9}}},{"hash":"d1ecf1d83860734522e02e6b09d28a664ab799e1","isMergeCommit":false,"messageTitle":"Improve UML diagrams","messageBody":"","fileTypesAndContributionMap":{"docs":{"insertions":23,"deletions":20}}},{"hash":"34b0d810ed8dd912bed210a945f4b65b163d7518","isMergeCommit":false,"messageTitle":"Improve formatting of test code","messageBody":"","fileTypesAndContributionMap":{"test-code":{"insertions":3,"deletions":6}}},{"hash":"da6f1c6af4ad1b0719289614ff70a5d0cdd3ecca","isMergeCommit":false,"messageTitle":"Add tests for null and valid cases in recall command","messageBody":"","fileTypesAndContributionMap":{"test-code":{"insertions":31,"deletions":0}}},{"hash":"ab81c1740d0393f0d78b4772389ca917a41fa1d4","isMergeCommit":true,"messageTitle":"Merge pull request #95 from Kokseng1/feature-86-UndoRedo","messageBody":"Implement undo-redo feature","fileTypesAndContributionMap":{}}]},{"date":"2023-10-27","commitResults":[{"hash":"e400b7f5b9365699c2a6207163e2bb372c7efe8e","isMergeCommit":true,"messageTitle":"Merge pull request #103 from alvinlim277/documentation-ShortcutsDevGuide","messageBody":"Update developer guide for shortcuts feature","fileTypesAndContributionMap":{}}]},{"date":"2023-10-28","commitResults":[{"hash":"ee6ea333567528d742db49ebb2887ecae29e1067","isMergeCommit":false,"messageTitle":"Handle duplicate commands properly in recall command","messageBody":"","fileTypesAndContributionMap":{"functional-code":{"insertions":6,"deletions":1},"test-code":{"insertions":12,"deletions":0}}}]},{"date":"2023-10-29","commitResults":[{"hash":"94d3a455a14fbb470fe9fa6d6bc0d104b678503a","isMergeCommit":false,"messageTitle":"Add theme command to change theme","messageBody":"","fileTypesAndContributionMap":{"functional-code":{"insertions":803,"deletions":46}}},{"hash":"aa5eded36040fa37b6a43db288895f3d49f5dbb0","isMergeCommit":false,"messageTitle":"Add tests for ThemeCommand and parser","messageBody":"","fileTypesAndContributionMap":{"functional-code":{"insertions":1,"deletions":0},"test-code":{"insertions":121,"deletions":4}}},{"hash":"66aa82eb695c2b1d861baa5bea2d8b2ccab6b39a","isMergeCommit":false,"messageTitle":"Fix bug making app unable to save user preferences","messageBody":"","fileTypesAndContributionMap":{"functional-code":{"insertions":126,"deletions":38},"test-code":{"insertions":0,"deletions":12}}},{"hash":"92641b116c1eade7c4ed12e089f196e23d51e911","isMergeCommit":false,"messageTitle":"Clean up code","messageBody":"","fileTypesAndContributionMap":{"functional-code":{"insertions":15,"deletions":116}}},{"hash":"81c9ce45e289f4ed5dc9a3a53f6a451665e32b95","isMergeCommit":false,"messageTitle":"Update user guide","messageBody":"","fileTypesAndContributionMap":{"functional-code":{"insertions":2,"deletions":2},"docs":{"insertions":29,"deletions":15}}},{"hash":"4ddf6d275a65f1113942cf19a8a240f9321d9855","isMergeCommit":false,"messageTitle":"Add newline at end of LightTheme.css","messageBody":"","fileTypesAndContributionMap":{"functional-code":{"insertions":1,"deletions":1}}},{"hash":"8ba505afc29d53d656e474e3491f7471a5f5e9c6","isMergeCommit":true,"messageTitle":"Merge pull request #110 from alvinlim277/bugfix-99-DuplicatePersons","messageBody":"Resolve duplicate person bug","fileTypesAndContributionMap":{}}]},{"date":"2023-10-31","commitResults":[{"hash":"598cd6e971d94dbf20343e2cbedd62db54313f57","isMergeCommit":true,"messageTitle":"Merge pull request #113 from alvinlim277/bugfix-109-PersonTypeBar","messageBody":"Fix PersonTypeBar bug","tags":["v1.3"],"fileTypesAndContributionMap":{}}]},{"date":"2023-11-02","commitResults":[{"hash":"46e3b09e74399e5c9030af7431c5de95b5279355","isMergeCommit":true,"messageTitle":"Merge pull request #116 from Gavino3o/bugfix-114-BasicComplexCommandMessages","messageBody":"Add useful error messages for Basic Commands","fileTypesAndContributionMap":{}}]},{"date":"2023-11-03","commitResults":[{"hash":"97b83746f27ea01a63a84e96802626052ecd71f9","isMergeCommit":true,"messageTitle":"Merge pull request #119 from Gavino3o/bugfix-UpdateReleaseNumber","messageBody":"Update app release version","tags":["v1.3.1"],"fileTypesAndContributionMap":{}}]},{"date":"2023-11-07","commitResults":[{"hash":"f7db517a8356539c0fcd7024857f118baa7b20f5","isMergeCommit":false,"messageTitle":"Fix bugs","messageBody":"","fileTypesAndContributionMap":{"functional-code":{"insertions":4,"deletions":33},"docs":{"insertions":9,"deletions":1},"test-code":{"insertions":0,"deletions":4}}},{"hash":"7a05951f42b126ca907381b0018a2b97341116b3","isMergeCommit":false,"messageTitle":"Update project portfolio page","messageBody":"","fileTypesAndContributionMap":{"docs":{"insertions":66,"deletions":42}}},{"hash":"dab4027f88ef0248e7908fd48839299919bacd55","isMergeCommit":false,"messageTitle":"Resolve checkstyle issues","messageBody":"","fileTypesAndContributionMap":{"functional-code":{"insertions":2,"deletions":4},"docs":{"insertions":1,"deletions":1}}},{"hash":"2edbe049aea6187ed6568896f262f689514e076c","isMergeCommit":false,"messageTitle":"Rephrase planned enhancement","messageBody":"","fileTypesAndContributionMap":{"docs":{"insertions":4,"deletions":3}}},{"hash":"ca919d0a78e0870aeb29c1c0cb2457da034d5864","isMergeCommit":true,"messageTitle":"Merge pull request #159 from vansh284/bugfixes-vansh-v1.4","messageBody":"Fix v1.4 bugs and update project portfolio page","fileTypesAndContributionMap":{}}]},{"date":"2023-11-10","commitResults":[{"hash":"d573bf4a379dd03b13bc305bcdb9773d93d9c7c7","isMergeCommit":true,"messageTitle":"Merge pull request #162 from angkyakdifp/Fix-Bug","messageBody":"Fix some bugs and add PPP","fileTypesAndContributionMap":{}},{"hash":"8b5e0c521589e726cd997ab0e22caf92295e346d","isMergeCommit":true,"messageTitle":"Merge pull request #160 from alvinlim277/bugfixes-v1.4","messageBody":"Fix bugs for v1.4","fileTypesAndContributionMap":{}}]},{"date":"2023-11-11","commitResults":[{"hash":"14776da26709e75ad9c0cbaf8007a090d0ed6c16","isMergeCommit":false,"messageTitle":"Fix minor errors in user guide","messageBody":"","fileTypesAndContributionMap":{"functional-code":{"insertions":1,"deletions":1},"docs":{"insertions":29,"deletions":25}}},{"hash":"74982c2dad4e7c6a3e7d4fd2f8416e587c9685e7","isMergeCommit":false,"messageTitle":"Fix some errors in developer guide","messageBody":"","fileTypesAndContributionMap":{"docs":{"insertions":58,"deletions":916}}},{"hash":"d0cc0e9c637e175a367206b2eb4e70a97f890464","isMergeCommit":false,"messageTitle":"Fix newline error","messageBody":"","fileTypesAndContributionMap":{"docs":{"insertions":1,"deletions":1}}},{"hash":"d92aa430ed227c1458bfc916a15cfd47cb42f667","isMergeCommit":false,"messageTitle":"Add couple of feature flaws","messageBody":"","fileTypesAndContributionMap":{"docs":{"insertions":8,"deletions":0}}}]},{"date":"2023-11-12","commitResults":[{"hash":"3153a9971b6f208aa317f5b90f943a38fb060506","isMergeCommit":true,"messageTitle":"Merge pull request #158 from Kokseng1/bugFix-107-UndoRedo","messageBody":"Fix undo redo bug","fileTypesAndContributionMap":{}},{"hash":"b4145b5718416048ede45505bc800362e2988f21","isMergeCommit":false,"messageTitle":"Fix some minor errors","messageBody":"","fileTypesAndContributionMap":{"functional-code":{"insertions":1,"deletions":1},"docs":{"insertions":17,"deletions":17}}},{"hash":"ab136c2d47433d717db0296b370ef9cccb8765bb","isMergeCommit":true,"messageTitle":"Merge pull request #175 from alvinlim277/documentation-fixes","messageBody":"Fix some errors in documentation","fileTypesAndContributionMap":{}},{"hash":"2039c22e457b005d8376a4801a55c4e019e626ed","isMergeCommit":true,"messageTitle":"Resolve merge conflict","messageBody":"","fileTypesAndContributionMap":{}},{"hash":"23d9d5a341240e213312fb89a3c1260b5b3c5142","isMergeCommit":false,"messageTitle":"Revert \"Add Some Constraint for Email, Location, and Phone Number\"","messageBody":"This reverts commit 97ac6d8d2dc42db4b32fd0042a333802987a7270.\n","fileTypesAndContributionMap":{"functional-code":{"insertions":5,"deletions":7},"docs":{"insertions":4,"deletions":9},"test-code":{"insertions":0,"deletions":10}}},{"hash":"c77a1e4827f775c0c97e49ef2b39b30262f8f5f4","isMergeCommit":false,"messageTitle":"Update user guide for person type flag","messageBody":"","fileTypesAndContributionMap":{"docs":{"insertions":5,"deletions":3}}},{"hash":"ec1843fe21b347c1b9237ee928ab68dfd1220673","isMergeCommit":false,"messageTitle":"Fix small error","messageBody":"","fileTypesAndContributionMap":{"docs":{"insertions":1,"deletions":1}}},{"hash":"40f4474b0f94f9a710e244a2727349190252f0c7","isMergeCommit":false,"messageTitle":"Enhance developer guide","messageBody":"","fileTypesAndContributionMap":{"docs":{"insertions":38,"deletions":4}}}]}],"Gavino3o":[{"date":"2023-09-25","commitResults":[{"hash":"4738c4459f4effb014394d3e8963d1874d7ad31d","isMergeCommit":false,"messageTitle":"Update AboutUs.md and add skeletal PPP","messageBody":"","fileTypesAndContributionMap":{"docs":{"insertions":35,"deletions":8}}},{"hash":"6f0c5fa67010d1dc33928611b6439266b8f17e52","isMergeCommit":false,"messageTitle":"Update \u0027list\u0027 feature information in UG","messageBody":"","fileTypesAndContributionMap":{"docs":{"insertions":8,"deletions":5}}},{"hash":"7f2a4def51f799cf8bb67954d1341b4b13e251c3","isMergeCommit":true,"messageTitle":"Merge pull request #21 from alvinlim277/documentation-19-UpdateReadMe","messageBody":"Update README, AboutUs and skeletal PPP","fileTypesAndContributionMap":{}},{"hash":"8002797e6569a98ecc2fb140c3b7f1a176b0e844","isMergeCommit":true,"messageTitle":"Merge pull request #20 from Gavino3o/documentation-18-InitialUG","messageBody":"Update \u0027list\u0027 feature information in UG","fileTypesAndContributionMap":{}}]},{"date":"2023-09-27","commitResults":[{"hash":"13b5156b7ecf9e97b539a616911e53b0d7bf6a73","isMergeCommit":false,"messageTitle":"Add list command use case in DeveloperGuide.md","messageBody":"","fileTypesAndContributionMap":{"docs":{"insertions":34,"deletions":0}}}]},{"date":"2023-09-29","commitResults":[{"hash":"f10a677f701833c96a17036ac52862a25cad4840","isMergeCommit":false,"messageTitle":"Add Customization and Shortcut User Stories","messageBody":"","fileTypesAndContributionMap":{"docs":{"insertions":14,"deletions":8}}}]},{"date":"2023-10-13","commitResults":[{"hash":"ed5e08b18c9c09b496fd5f614e8e3f94b32bdc03","isMergeCommit":false,"messageTitle":"Implement Find Specialist by prefixes","messageBody":"","fileTypesAndContributionMap":{"functional-code":{"insertions":303,"deletions":4},"other":{"insertions":2,"deletions":1},"test-code":{"insertions":6,"deletions":5}}},{"hash":"2a7f1afeb7ae897f8d06e441d5514097de156885","isMergeCommit":true,"messageTitle":"Merge branch \u0027master\u0027 into feature-10-FindByPrefix","messageBody":"","fileTypesAndContributionMap":{}},{"hash":"741ab0c60991e3c49532b513c37d73582a6bec99","isMergeCommit":false,"messageTitle":"Implement parsePatient for FindCommandParser","messageBody":"","fileTypesAndContributionMap":{"functional-code":{"insertions":129,"deletions":33}}},{"hash":"9b822f1ec5ca2f16cc9513ffb1ab4fe4dddd230e","isMergeCommit":false,"messageTitle":"Add JavaDocs and Checkstyle for Predicates and FindCommand","messageBody":"","fileTypesAndContributionMap":{"functional-code":{"insertions":48,"deletions":30}}},{"hash":"b746b054d18eb4b9f8eabf0ac9271f5fcce0413b","isMergeCommit":false,"messageTitle":"Fix import order in TagContainsKeywordsPredicate","messageBody":"","fileTypesAndContributionMap":{"functional-code":{"insertions":3,"deletions":4}}},{"hash":"2fe2ed92a95d98ad895c1d691c83965cafa44c83","isMergeCommit":false,"messageTitle":"Fix incorrect import order in test files","messageBody":"","fileTypesAndContributionMap":{"test-code":{"insertions":6,"deletions":4}}}]},{"date":"2023-10-14","commitResults":[{"hash":"4c27f61c3bd2d27413c730ab36efe0aeb3e45cde","isMergeCommit":false,"messageTitle":"Modify tests for new FindCommand Syntax","messageBody":"","fileTypesAndContributionMap":{"functional-code":{"insertions":15,"deletions":3},"test-code":{"insertions":84,"deletions":20}}}]},{"date":"2023-10-16","commitResults":[{"hash":"80f0802f8a83cd9f25837bc22d31174e668e4e72","isMergeCommit":false,"messageTitle":"Improve readability of Lambda Functions","messageBody":"","fileTypesAndContributionMap":{"functional-code":{"insertions":6,"deletions":3}}},{"hash":"531c2a60455896d80860ef716f2163b0e1975c42","isMergeCommit":false,"messageTitle":"Add toString and empty argument tests for Find Command","messageBody":"","fileTypesAndContributionMap":{"test-code":{"insertions":142,"deletions":5}}},{"hash":"9f01a6558f09a65529cf5bbe5bf5070e4c893447","isMergeCommit":false,"messageTitle":"Add FindPredicateMap","messageBody":"","fileTypesAndContributionMap":{"functional-code":{"insertions":64,"deletions":0}}},{"hash":"6ba7d07c5f3648c439247b9f5bedc29b6c2bd3c5","isMergeCommit":false,"messageTitle":"Implement Partial FindCommand Test","messageBody":"","fileTypesAndContributionMap":{"functional-code":{"insertions":7,"deletions":7},"test-code":{"insertions":63,"deletions":5}}},{"hash":"ffd78b111d0119ee37daf96ad422945980653cf6","isMergeCommit":true,"messageTitle":"Merge branch \u0027master\u0027 into test-71-FindCommandCodeCov","messageBody":"","fileTypesAndContributionMap":{}}]},{"date":"2023-10-17","commitResults":[{"hash":"e07868bcba10bd9395df4fe4ad479b50d252a713","isMergeCommit":false,"messageTitle":"Incorporate new FindPredicateMap into tests","messageBody":"","fileTypesAndContributionMap":{"functional-code":{"insertions":46,"deletions":49},"test-code":{"insertions":132,"deletions":136}}},{"hash":"3c60313ee7386378d7abb2396fdac84eab00d798","isMergeCommit":false,"messageTitle":"Fix Checkstyle issues","messageBody":"","fileTypesAndContributionMap":{"functional-code":{"insertions":2,"deletions":1},"test-code":{"insertions":0,"deletions":13}}},{"hash":"716c07d51a85ad3b728d5ff2257e39f4f39561c3","isMergeCommit":false,"messageTitle":"Empty Commit","messageBody":"","fileTypesAndContributionMap":{"docs":{"insertions":0,"deletions":1}}},{"hash":"13b9702f3cecbcd3ba573c3f09a308b35b8775be","isMergeCommit":false,"messageTitle":"Add FindCommandParser Tests","messageBody":"","fileTypesAndContributionMap":{"test-code":{"insertions":116,"deletions":11}}},{"hash":"6dac05d58fd6d44aaf9be94619629dad44ba8242","isMergeCommit":false,"messageTitle":"Update FindCommand in User Guide","messageBody":"","fileTypesAndContributionMap":{"docs":{"insertions":11,"deletions":7}}},{"hash":"b728a48bcd869aa2a5b7ffb5a7c029b4fda8740c","isMergeCommit":false,"messageTitle":"Modify FindCommandParserTest to use existing Parsing Util","messageBody":"","fileTypesAndContributionMap":{"test-code":{"insertions":26,"deletions":34}}},{"hash":"55b5e2a04ba48560a90a570cfa431cbc3f6cea7a","isMergeCommit":false,"messageTitle":"Remove unused imports in tests","messageBody":"","fileTypesAndContributionMap":{"test-code":{"insertions":0,"deletions":2}}}]},{"date":"2023-10-19","commitResults":[{"hash":"41e7f4b43d1ad53e0ce9e6ecb7bf52184999761f","isMergeCommit":false,"messageTitle":"Fix Find Command Invalid Argument Parsing","messageBody":"","fileTypesAndContributionMap":{"functional-code":{"insertions":10,"deletions":10},"test-code":{"insertions":3,"deletions":3}}}]},{"date":"2023-10-20","commitResults":[{"hash":"22ce7c1ddaa23178fa9ff38ca49a96b36e8ea6be","isMergeCommit":false,"messageTitle":"Add Invalid Preamble Test for Find Command","messageBody":"","fileTypesAndContributionMap":{"test-code":{"insertions":9,"deletions":1}}}]},{"date":"2023-10-21","commitResults":[{"hash":"f3372dbca040160322272f4c450240930f3b1d7d","isMergeCommit":true,"messageTitle":"Merge pull request #83 from vansh284/update-version-number","messageBody":"Update version number for trial JAR release","tags":["v1.2.1"],"fileTypesAndContributionMap":{}},{"hash":"c0104fd284c1237b6f3dbbdc95a8d5cea8a91554","isMergeCommit":false,"messageTitle":"Update FindCommand Expected Behavior in UG","messageBody":"","fileTypesAndContributionMap":{"docs":{"insertions":1,"deletions":0}}}]},{"date":"2023-10-23","commitResults":[{"hash":"276d2b0f5563809010028c53ecc895f4fbd90ded","isMergeCommit":false,"messageTitle":"Implement Multiple Index Deletion","messageBody":"","fileTypesAndContributionMap":{"functional-code":{"insertions":72,"deletions":19},"test-code":{"insertions":65,"deletions":31}}},{"hash":"aac934bc05ec30898a6f91733bf72c1c010786ef","isMergeCommit":true,"messageTitle":"Merge branch \u0027master\u0027 into feature-31-DeleteCommandMassOps","messageBody":"","fileTypesAndContributionMap":{}},{"hash":"c2a5437e5b02d7e2e4a3846c55e0c7b24d9d6a9c","isMergeCommit":false,"messageTitle":"Add more tests for DeleteCommandParserTest","messageBody":"","fileTypesAndContributionMap":{"functional-code":{"insertions":0,"deletions":1},"test-code":{"insertions":16,"deletions":1}}}]},{"date":"2023-10-24","commitResults":[{"hash":"21669f594c40613a1b96b4b5138650eac6efe1de","isMergeCommit":false,"messageTitle":"Fix Delete Command duplicate index error","messageBody":"","fileTypesAndContributionMap":{"functional-code":{"insertions":41,"deletions":11},"test-code":{"insertions":21,"deletions":6}}},{"hash":"df6904bb4b809d4518a980480747f311057a73b6","isMergeCommit":false,"messageTitle":"Update Delete Command guide in UserGuide.md","messageBody":"","fileTypesAndContributionMap":{"functional-code":{"insertions":1,"deletions":1},"docs":{"insertions":10,"deletions":6}}},{"hash":"07cef16c6d837895e7a1b1969105918313906660","isMergeCommit":false,"messageTitle":"Modify DeleteCommandParser validity check order","messageBody":"","fileTypesAndContributionMap":{"functional-code":{"insertions":3,"deletions":2}}}]},{"date":"2023-10-25","commitResults":[{"hash":"ac85bd89867fa4222a27ae1cd9ea42d43e3d7848","isMergeCommit":false,"messageTitle":"Fix Typo in UserGuide.md","messageBody":"","fileTypesAndContributionMap":{"docs":{"insertions":1,"deletions":1}}},{"hash":"8c960057fdd33f9e569cc01c6753cf914eb74668","isMergeCommit":true,"messageTitle":"Merge pull request #89 from Gavino3o/feature-31-DeleteCommandMassOps","messageBody":"Delete Command Mass Operation","fileTypesAndContributionMap":{}}]},{"date":"2023-10-27","commitResults":[{"hash":"0f1b2a507dc56917eb80caf67968700f2358b847","isMergeCommit":false,"messageTitle":"Add Find Command Feature to DeveloperGuide.md","messageBody":"","fileTypesAndContributionMap":{"docs":{"insertions":135,"deletions":0}}},{"hash":"d204d2cf9bcd0aa590caffb4c689b75b2902706f","isMergeCommit":false,"messageTitle":"Add newlines to end of .puml files","messageBody":"","fileTypesAndContributionMap":{"docs":{"insertions":2,"deletions":2}}},{"hash":"6c8c322102cfc780cc74c4d786d0b2c32db66997","isMergeCommit":true,"messageTitle":"Resolve merge conflict with master","messageBody":"","fileTypesAndContributionMap":{}},{"hash":"e01b291bcdae21eddfa548c3ff41d34fc99a74f7","isMergeCommit":true,"messageTitle":"Merge pull request #104 from Gavino3o/documentation-31-DGFindFeature","messageBody":"Add Find Command Feature to DeveloperGuide.md","fileTypesAndContributionMap":{}},{"hash":"08d16eaa2ae1e0e9aebe3ed128ec85ae6053e26e","isMergeCommit":false,"messageTitle":"Remove index parsing from EditCommand","messageBody":"","fileTypesAndContributionMap":{"functional-code":{"insertions":31,"deletions":66},"test-code":{"insertions":22,"deletions":38}}},{"hash":"d43d7e93c642fe28c0d716f6533dabe73a873228","isMergeCommit":false,"messageTitle":"Fix EditDescriptor ClassCastException","messageBody":"","fileTypesAndContributionMap":{"functional-code":{"insertions":26,"deletions":18}}}]},{"date":"2023-10-28","commitResults":[{"hash":"cb3aefc318347cfef5c6eb0b815a844bf4a6ac0e","isMergeCommit":false,"messageTitle":"Add Prefix Argument Check","messageBody":"","fileTypesAndContributionMap":{"functional-code":{"insertions":26,"deletions":5}}},{"hash":"d9ec37bab9280e17b331d97edf25b06c2ccb6eb0","isMergeCommit":false,"messageTitle":"Add more usefull messages for Invalid Edit Command","messageBody":"","fileTypesAndContributionMap":{"functional-code":{"insertions":11,"deletions":1}}},{"hash":"766079784dea31790943f3b3d9b9687810f6a66b","isMergeCommit":false,"messageTitle":"Modify tests for new Edit Command format","messageBody":"","fileTypesAndContributionMap":{"functional-code":{"insertions":5,"deletions":4},"test-code":{"insertions":116,"deletions":97}}}]},{"date":"2023-10-29","commitResults":[{"hash":"69076acb04639ffe4b101754d3b24f6011bda0d8","isMergeCommit":false,"messageTitle":"Fix Checkstyle Errors","messageBody":"","fileTypesAndContributionMap":{"functional-code":{"insertions":0,"deletions":3},"test-code":{"insertions":3,"deletions":16}}},{"hash":"8c69021cdc69f4fb37323577756148bf401c31d3","isMergeCommit":false,"messageTitle":"Add missing Specialist location non-Null check","messageBody":"","fileTypesAndContributionMap":{"functional-code":{"insertions":1,"deletions":1}}},{"hash":"ae8ee5659cdd2a6de41622c98c2b210a6e2a872d","isMergeCommit":false,"messageTitle":"Add Edit Command information to User Guide","messageBody":"","fileTypesAndContributionMap":{"docs":{"insertions":30,"deletions":4}}},{"hash":"c9e1033419a48824572bda57382249f7e80885c2","isMergeCommit":false,"messageTitle":"Improve Code Coverage","messageBody":"","fileTypesAndContributionMap":{"functional-code":{"insertions":4,"deletions":7},"test-code":{"insertions":24,"deletions":0}}},{"hash":"f55cc2d0dd3527d21cdb1147fa3406fd2e60d8e3","isMergeCommit":false,"messageTitle":"Add missing Edit Command in Summary Table","messageBody":"","fileTypesAndContributionMap":{"docs":{"insertions":5,"deletions":4}}},{"hash":"dd46a29987466557d1b71339ff04b8bb1effe05c","isMergeCommit":false,"messageTitle":"Add test for Edit Commmand Complex Scenario","messageBody":"","fileTypesAndContributionMap":{"test-code":{"insertions":25,"deletions":0}}}]},{"date":"2023-11-01","commitResults":[{"hash":"8458d9c439d6e7f241086e04a2e265ae9870fe92","isMergeCommit":false,"messageTitle":"Add useful error messages for Basic Commands","messageBody":"","fileTypesAndContributionMap":{"functional-code":{"insertions":29,"deletions":1}}},{"hash":"d8a673f0a44f7d34564b29f7e3592c18adc1be43","isMergeCommit":false,"messageTitle":"Remove unused import","messageBody":"","fileTypesAndContributionMap":{"functional-code":{"insertions":0,"deletions":1}}},{"hash":"00e2336785b6fab75e1a34d99a74de5c5a539840","isMergeCommit":false,"messageTitle":"Add tests for parsing Basic commands as Complex Commands","messageBody":"","fileTypesAndContributionMap":{"test-code":{"insertions":42,"deletions":0}}}]},{"date":"2023-11-02","commitResults":[{"hash":"53c54ec311a6d7f3d4fa322c809826cce43c7fce","isMergeCommit":true,"messageTitle":"Merge pull request #115 from Kokseng1/bugFix-107-UndoRedo","messageBody":"Update undo/redo commands to include addsc command","fileTypesAndContributionMap":{}},{"hash":"48a06e46c5a4eea3e1b84761927ed33b7182622e","isMergeCommit":false,"messageTitle":"Update Help Command URL","messageBody":"","fileTypesAndContributionMap":{"functional-code":{"insertions":1,"deletions":1}}},{"hash":"54e0fd57d4bee6290291093c2707d5ae1c96ec87","isMergeCommit":false,"messageTitle":"Update UG and MainApp Version","messageBody":"","fileTypesAndContributionMap":{"functional-code":{"insertions":1,"deletions":1},"docs":{"insertions":39,"deletions":25}}}]},{"date":"2023-11-03","commitResults":[{"hash":"36c2cd3ae5c04059254dd879224fad7d23a48454","isMergeCommit":false,"messageTitle":"Update App Release Version","messageBody":"","fileTypesAndContributionMap":{"functional-code":{"insertions":1,"deletions":1}}}]},{"date":"2023-11-07","commitResults":[{"hash":"e9cd610ba1b96b4f3ad15d84d643380d1bbc5722","isMergeCommit":false,"messageTitle":"Update title and description of index.md","messageBody":"","fileTypesAndContributionMap":{"docs":{"insertions":4,"deletions":4}}},{"hash":"93daaca64be7e8f01a7243e077f51a9942df442e","isMergeCommit":false,"messageTitle":"Fix Optional Fields notation in error messages","messageBody":"","fileTypesAndContributionMap":{"functional-code":{"insertions":18,"deletions":19}}},{"hash":"d8e0895a79f5d54c80eb592ec98e8ca60b78cf87","isMergeCommit":false,"messageTitle":"Add delete inconsistency to Planned Enhancements","messageBody":"","fileTypesAndContributionMap":{"docs":{"insertions":7,"deletions":0}}},{"hash":"d0e10614dff7bec008992d4c494503b56dc864e3","isMergeCommit":false,"messageTitle":"Update Gavino3o PPP","messageBody":"","fileTypesAndContributionMap":{"docs":{"insertions":35,"deletions":9}}},{"hash":"fda7f73fc80e257399415ad1eefcee7eed6f2f45","isMergeCommit":false,"messageTitle":"Fix EditCommandParser test cases","messageBody":"","fileTypesAndContributionMap":{"test-code":{"insertions":2,"deletions":1}}},{"hash":"400a08755f6a55ca7d58813f288b288c076913f4","isMergeCommit":false,"messageTitle":"Add Edit Patient test case","messageBody":"","fileTypesAndContributionMap":{"test-code":{"insertions":2,"deletions":0}}}]},{"date":"2023-11-08","commitResults":[{"hash":"529bdef2e344d612c9b36bda4845a8ec896ed1a8","isMergeCommit":false,"messageTitle":"Fix typo in DG","messageBody":"","fileTypesAndContributionMap":{"docs":{"insertions":1,"deletions":1}}},{"hash":"81ba5e82fcc5c846cbf577c779ddde5169b3a5da","isMergeCommit":true,"messageTitle":"Resolve comments and merge conflict","messageBody":"","fileTypesAndContributionMap":{}},{"hash":"5f06936d29766fb340dfbb7af63f055e98a0f7f4","isMergeCommit":true,"messageTitle":"Merge pull request #161 from Gavino3o/bugfix-gavin-v1.4","messageBody":"Various documentation updates and bugfixes","fileTypesAndContributionMap":{}}]},{"date":"2023-11-12","commitResults":[{"hash":"ed77c71d138ff1c35c706771c5c2046eb6145652","isMergeCommit":true,"messageTitle":"Merge pull request #169 from vansh284/documentation-minorFixes","messageBody":"Fix minor issues in documentation","fileTypesAndContributionMap":{}},{"hash":"a8a86358cdd875ede689310a8ead3b53e7774867","isMergeCommit":false,"messageTitle":"Improve specificity of command format in UG","messageBody":"","fileTypesAndContributionMap":{"docs":{"insertions":19,"deletions":13}}},{"hash":"ad33c3f4ec9b51d2b22e3719989a160a05025a24","isMergeCommit":false,"messageTitle":"Fix errors in Find Command UML diagrams","messageBody":"","fileTypesAndContributionMap":{"docs":{"insertions":5,"deletions":2}}},{"hash":"a963927478cb25f932aac5c1119486d00bcc035a","isMergeCommit":false,"messageTitle":"Add Manual Testing Instructions","messageBody":"Instructions are added for add, view, edit, and delete commands.\n","fileTypesAndContributionMap":{"docs":{"insertions":72,"deletions":24}}},{"hash":"e8e2d52f1dea062b656519b8eb9e783038af0003","isMergeCommit":false,"messageTitle":"Add more manual testing instructions in DG","messageBody":"Add initial documentation for manual testing instructions of find, undo, redo, addsc, and delsc commands.\n","fileTypesAndContributionMap":{"docs":{"insertions":99,"deletions":42}}},{"hash":"f067c9b6a5bddaaea5894e1fdca450a37abb06e9","isMergeCommit":true,"messageTitle":"Merge pull request #177 from Gavino3o/documentation-170-ManualTestingInstr","messageBody":"Documentation Updates","fileTypesAndContributionMap":{}}]}],"angkyakdifp":[{"date":"2023-10-04","commitResults":[{"hash":"2655a71c363ba4e72daf0e7b6f14da6e913f0b1a","isMergeCommit":false,"messageTitle":"Add Skeletal PPP","messageBody":"","fileTypesAndContributionMap":{"docs":{"insertions":31,"deletions":51}}},{"hash":"daa4c38a78e8686aa83303f7bdc2d0de78d0f086","isMergeCommit":false,"messageTitle":"Add Quick Start Use Case","messageBody":"","fileTypesAndContributionMap":{"docs":{"insertions":23,"deletions":0}}},{"hash":"622f97245909e1a1ed015c3cbfe590637ac8b06d","isMergeCommit":false,"messageTitle":"Edit Quick Start for the User Guide","messageBody":"","fileTypesAndContributionMap":{"docs":{"insertions":7,"deletions":30}}},{"hash":"e8204d0636e52282f33fad0730ea652784cd4efb","isMergeCommit":false,"messageTitle":"Add a Use Case: Searching for Patients.","messageBody":"","fileTypesAndContributionMap":{"docs":{"insertions":23,"deletions":0}}}]},{"date":"2023-10-05","commitResults":[{"hash":"bae5f4236479c06ecd960c440d56a8740d76d03c","isMergeCommit":false,"messageTitle":"Update DeveloperGuide.md","messageBody":"","fileTypesAndContributionMap":{"docs":{"insertions":1,"deletions":1}}},{"hash":"a48eabde62546ac7fa2b3714c669545fe356645a","isMergeCommit":false,"messageTitle":"Add Specialist Management User Guide","messageBody":"","fileTypesAndContributionMap":{"docs":{"insertions":29,"deletions":25}}},{"hash":"0bb8941d763e0e5878d90fb0d949da14f0156123","isMergeCommit":false,"messageTitle":"Update DeveloperGuide.md","messageBody":"","fileTypesAndContributionMap":{"docs":{"insertions":5,"deletions":5}}}]},{"date":"2023-10-13","commitResults":[{"hash":"f14ec9680cb63148fcdeb2ed53f5a83c1d3264b3","isMergeCommit":true,"messageTitle":"Merge pull request #1 from AY2324S1-CS2103T-W13-1/master","messageBody":"Updating team code","fileTypesAndContributionMap":{}},{"hash":"db9c238958ccfdc80aeddd43cee62d8f5d67a48e","isMergeCommit":false,"messageTitle":"Add Medical History Field for Patient","messageBody":"","fileTypesAndContributionMap":{"functional-code":{"insertions":191,"deletions":34},"test-code":{"insertions":138,"deletions":23}}},{"hash":"95b839ac983214400049c717a3b7f88a194f7519","isMergeCommit":false,"messageTitle":"Fixing bugs in equal method","messageBody":"","fileTypesAndContributionMap":{"functional-code":{"insertions":1,"deletions":1},"test-code":{"insertions":6,"deletions":3}}},{"hash":"2abf324116b508f27db8c05faaaeb39159e77104","isMergeCommit":false,"messageTitle":"Resolving Conflict","messageBody":"","fileTypesAndContributionMap":{"test-code":{"insertions":5,"deletions":13}}},{"hash":"e5848bcda6052b2fd5b61724e17115da50d0c360","isMergeCommit":true,"messageTitle":"Merge pull request #2 from AY2324S1-CS2103T-W13-1/master","messageBody":"Updating the Team Code","fileTypesAndContributionMap":{}},{"hash":"7b184ac23b2ae6cac868c444c8e005053a06a44d","isMergeCommit":false,"messageTitle":"Fix Testing","messageBody":"","fileTypesAndContributionMap":{"test-code":{"insertions":6,"deletions":3}}},{"hash":"51959ad445b06755053fe2a0732423b881c95255","isMergeCommit":false,"messageTitle":"Improving Checkstyle","messageBody":"","fileTypesAndContributionMap":{"test-code":{"insertions":47,"deletions":40}}},{"hash":"a6fd480a136921eaf0ed6e642df0c4cd964e6f9a","isMergeCommit":false,"messageTitle":"Improving Checkstyle","messageBody":"","fileTypesAndContributionMap":{"functional-code":{"insertions":31,"deletions":7}}},{"hash":"996257a37b8f2e9af76fae0405fc4c532ad5aab1","isMergeCommit":false,"messageTitle":"Improving Checkstyle","messageBody":"","fileTypesAndContributionMap":{"test-code":{"insertions":37,"deletions":27}}},{"hash":"275afb032f67be30d5d7259ae73c3c9f05c8779e","isMergeCommit":false,"messageTitle":"Fixing Build Failure","messageBody":"","fileTypesAndContributionMap":{"functional-code":{"insertions":2,"deletions":1},"test-code":{"insertions":7,"deletions":6}}},{"hash":"d87802e46f685e8032dd0bb4360271dd6432a977","isMergeCommit":false,"messageTitle":"Add Testing","messageBody":"","fileTypesAndContributionMap":{"test-code":{"insertions":8,"deletions":5}}},{"hash":"f77ca31ec867b080ea7573faa33d6fdb738a4b2c","isMergeCommit":false,"messageTitle":"Fixing Minor Error","messageBody":"","fileTypesAndContributionMap":{"functional-code":{"insertions":3,"deletions":3},"test-code":{"insertions":2,"deletions":2}}},{"hash":"53134411a6ec1ded07799967dbc110560525d536","isMergeCommit":false,"messageTitle":"Fixing Minor Error","messageBody":"","fileTypesAndContributionMap":{"test-code":{"insertions":6,"deletions":1}}},{"hash":"09785f2e14394f724cdb984ec3e56be8eef5abe5","isMergeCommit":false,"messageTitle":"Fixing Minor Error","messageBody":"","fileTypesAndContributionMap":{"test-code":{"insertions":7,"deletions":5}}},{"hash":"c83f4fb24466ce8eb52e3dec490afb1205cc0830","isMergeCommit":false,"messageTitle":"Adding Equals Testing","messageBody":"","fileTypesAndContributionMap":{"test-code":{"insertions":19,"deletions":7}}}]},{"date":"2023-10-17","commitResults":[{"hash":"fc0bce9f06237b7dd60250e769f22a096d4d0997","isMergeCommit":true,"messageTitle":"Merge pull request #3 from AY2324S1-CS2103T-W13-1/master","messageBody":"Update Team Code","fileTypesAndContributionMap":{}},{"hash":"0fcf04d748f8407740dac8a8934f3eda64a613cc","isMergeCommit":false,"messageTitle":"Change the Property of Medical History","messageBody":"","fileTypesAndContributionMap":{"functional-code":{"insertions":139,"deletions":46},"test-code":{"insertions":41,"deletions":49}}},{"hash":"b639284af36c5adc3b4bb1cbc1726a30770fae5d","isMergeCommit":false,"messageTitle":"Change the Property of Medical History","messageBody":"","fileTypesAndContributionMap":{"test-code":{"insertions":4,"deletions":3}}},{"hash":"0f4013d25c151aa6f6e7f2c1c2ad9def3c5acb64","isMergeCommit":false,"messageTitle":"Add Testing for MedHistoryContainsKeywordsPredicate Class","messageBody":"","fileTypesAndContributionMap":{"test-code":{"insertions":93,"deletions":0}}},{"hash":"7d89954a13ed0dc9ad4575a1b940831620ae00e1","isMergeCommit":false,"messageTitle":"Fixing Checkstyle","messageBody":"","fileTypesAndContributionMap":{"test-code":{"insertions":27,"deletions":16}}},{"hash":"382873ba95d686099cee76987e8f76e894217b10","isMergeCommit":false,"messageTitle":"Add Testing for JsonAdaptedMedicalHistory Class","messageBody":"","fileTypesAndContributionMap":{"test-code":{"insertions":12,"deletions":0}}},{"hash":"d5baf28b38807d38b3f2f31382735cb2fadfed15","isMergeCommit":false,"messageTitle":"Add Testing for MedHistoryContainsKeywordsPredicate Class","messageBody":"","fileTypesAndContributionMap":{"test-code":{"insertions":1,"deletions":1}}}]},{"date":"2023-10-20","commitResults":[{"hash":"7dfa1a8b8ba42f2978cc4967069477803d876d35","isMergeCommit":true,"messageTitle":"Merge pull request #4 from AY2324S1-CS2103T-W13-1/master","messageBody":"Merging Team Code","fileTypesAndContributionMap":{}},{"hash":"cf399aacd186dfcfc01ee893c23a7a66808948f1","isMergeCommit":false,"messageTitle":"Fixing Bug for Medical History display","messageBody":"","fileTypesAndContributionMap":{"functional-code":{"insertions":15,"deletions":0}}}]},{"date":"2023-10-24","commitResults":[{"hash":"8a94a219a98e88569d265382025839888e330238","isMergeCommit":true,"messageTitle":"Merge pull request #5 from AY2324S1-CS2103T-W13-1/master","messageBody":"Merge Team Code","fileTypesAndContributionMap":{}}]},{"date":"2023-10-25","commitResults":[{"hash":"63c639bdd420a407b403cc7cea510150701a5953","isMergeCommit":false,"messageTitle":"Improve UI and Adding View Command","messageBody":"","fileTypesAndContributionMap":{"functional-code":{"insertions":523,"deletions":37}}},{"hash":"36e313aa4b7a322db203083350242be6f80650f9","isMergeCommit":false,"messageTitle":"Create Testing for View Command","messageBody":"","fileTypesAndContributionMap":{"functional-code":{"insertions":33,"deletions":30},"test-code":{"insertions":167,"deletions":0}}},{"hash":"8da4ce91f1a1493ef03093aef7450f1d1d9a4c6c","isMergeCommit":false,"messageTitle":"Add Some Testing for AddressBookParserTest and LogicManagerTest","messageBody":"","fileTypesAndContributionMap":{"test-code":{"insertions":13,"deletions":3}}},{"hash":"a27206338092b345c04f8e56bb8f0d709f7f3184","isMergeCommit":false,"messageTitle":"Add Some Testing for Equals Method","messageBody":"","fileTypesAndContributionMap":{"test-code":{"insertions":4,"deletions":0}}},{"hash":"079024f2d977be63cceba9f94e4a0f2d1bbc3fd3","isMergeCommit":false,"messageTitle":"Fixing Bug for an Empty AddressBook","messageBody":"","fileTypesAndContributionMap":{"functional-code":{"insertions":3,"deletions":1}}},{"hash":"7d953999096b93a8ebc307825d99f3538669ff84","isMergeCommit":false,"messageTitle":"Add Testing for Model Manager","messageBody":"","fileTypesAndContributionMap":{"test-code":{"insertions":14,"deletions":0}}},{"hash":"6b1684a0a4b4a82d9d6321bf9093c652cb6f5b84","isMergeCommit":false,"messageTitle":"Fix CheckStyle","messageBody":"","fileTypesAndContributionMap":{"test-code":{"insertions":0,"deletions":1}}}]},{"date":"2023-10-26","commitResults":[{"hash":"bac3b21110218c3a934c76478903f5e8e8c48a0e","isMergeCommit":false,"messageTitle":"Adding Abstract Method for isSelectedEmpty()","messageBody":"","fileTypesAndContributionMap":{"functional-code":{"insertions":4,"deletions":0},"test-code":{"insertions":5,"deletions":0}}},{"hash":"755688371136961bdc001435b2915aba5fa02c90","isMergeCommit":true,"messageTitle":"Merge pull request #6 from AY2324S1-CS2103T-W13-1/master","messageBody":"Merge Team Code","fileTypesAndContributionMap":{}},{"hash":"b1f9c8ee9e622d9463a6772fcb05ceca3e92e8c7","isMergeCommit":false,"messageTitle":"Resolve Conflict","messageBody":"","fileTypesAndContributionMap":{"functional-code":{"insertions":1,"deletions":21}}},{"hash":"be5fd8e0caa81d9a75ee25f67baa892cc736ea3f","isMergeCommit":false,"messageTitle":"Resolve Conflict","messageBody":"","fileTypesAndContributionMap":{"functional-code":{"insertions":0,"deletions":5}}},{"hash":"98710de01b0ddfeba5bcb4ce782ce2a355ea8d9a","isMergeCommit":false,"messageTitle":"Resolve Conflict","messageBody":"","fileTypesAndContributionMap":{"functional-code":{"insertions":59,"deletions":0}}},{"hash":"4801c13f894ce8f97b1b68efbf5e8186fcb5434f","isMergeCommit":false,"messageTitle":"Resolve Conflict","messageBody":"","fileTypesAndContributionMap":{"functional-code":{"insertions":0,"deletions":34}}},{"hash":"636410beeaf86f268ad0776352286ca2f1a02c4c","isMergeCommit":true,"messageTitle":"Merge branch \u0027master\u0027 into branch-UI-Improvisation","messageBody":"","fileTypesAndContributionMap":{}},{"hash":"48015e830be23d747d8f820914becb7e8ac21a10","isMergeCommit":false,"messageTitle":"Resolve Conflict","messageBody":"","fileTypesAndContributionMap":{"functional-code":{"insertions":0,"deletions":3}}},{"hash":"e2fa35635ecbfd7e74aa277cd65fbb791f1bbd17","isMergeCommit":true,"messageTitle":"Merge branch \u0027branch-UI-Improvisation\u0027 of https://github.com/angkyakdifp/tp into branch-UI-Improvisation","messageBody":"","fileTypesAndContributionMap":{}},{"hash":"60ed9803f906b78fbb44bf6cb96c34b15692f32d","isMergeCommit":false,"messageTitle":"Fix CheckStyle","messageBody":"","fileTypesAndContributionMap":{"functional-code":{"insertions":5,"deletions":1}}},{"hash":"459f69f3772553b81361e223f0653aedef3e4acf","isMergeCommit":true,"messageTitle":"Merge branch \u0027master\u0027 into branch-UI-Improvisation","messageBody":"","fileTypesAndContributionMap":{}},{"hash":"0a69d293e89fb209f65416ec8c0388ef4afa7e5e","isMergeCommit":false,"messageTitle":"Resolve Conflict","messageBody":"","fileTypesAndContributionMap":{"functional-code":{"insertions":2,"deletions":2},"test-code":{"insertions":4,"deletions":6}}},{"hash":"2df6b7a6e9f002190d962d6125ca9341dc265c5a","isMergeCommit":true,"messageTitle":"Merge pull request #92 from angkyakdifp/branch-UI-Improvisation","messageBody":"UI Improvisation and Add View Command","fileTypesAndContributionMap":{}},{"hash":"4d485f0aa72b99d9d4115aff7d003ce809d74ac6","isMergeCommit":false,"messageTitle":"Improve Developer Guide","messageBody":"","fileTypesAndContributionMap":{"docs":{"insertions":201,"deletions":0}}}]},{"date":"2023-10-27","commitResults":[{"hash":"4598bf2fde291929607697fe22da9b262264eeb7","isMergeCommit":false,"messageTitle":"Fix some minor issues","messageBody":"","fileTypesAndContributionMap":{"docs":{"insertions":11,"deletions":13}}}]},{"date":"2023-10-29","commitResults":[{"hash":"6606a5bc7f16e5fbcdf49d79304885acae54e15b","isMergeCommit":true,"messageTitle":"Merge pull request #8 from AY2324S1-CS2103T-W13-1/master","messageBody":"Merge Code","fileTypesAndContributionMap":{}},{"hash":"e52a59829231c38f1435d918d45fd571e9e8e9e4","isMergeCommit":true,"messageTitle":"Merge pull request #9 from AY2324S1-CS2103T-W13-1/master","messageBody":"Merge Code","fileTypesAndContributionMap":{}}]},{"date":"2023-11-01","commitResults":[{"hash":"6770891f6d3e5d403c017aaaba6415df10264d28","isMergeCommit":true,"messageTitle":"Merge pull request #10 from AY2324S1-CS2103T-W13-1/master","messageBody":"Merge Code","fileTypesAndContributionMap":{}},{"hash":"b20413bb910608e587d73c785ef9a9255d9e7191","isMergeCommit":false,"messageTitle":"Fix Some Bug","messageBody":"","fileTypesAndContributionMap":{"functional-code":{"insertions":26,"deletions":84},"other":{"insertions":0,"deletions":0},"test-code":{"insertions":18,"deletions":2}}}]},{"date":"2023-11-02","commitResults":[{"hash":"9af37ceb69a1564a9f7bdb4da36fde2384db7785","isMergeCommit":false,"messageTitle":"Remove Unused Method","messageBody":"","fileTypesAndContributionMap":{"functional-code":{"insertions":0,"deletions":4}}},{"hash":"7454e07499b3b704e6add0cab9a0a0b8e2927dd6","isMergeCommit":true,"messageTitle":"Merge pull request #117 from angkyakdifp/Fixing-UI-Bug","messageBody":"Fixing UI bug and Enlarge the Ouput Command Box","fileTypesAndContributionMap":{}}]},{"date":"2023-11-08","commitResults":[{"hash":"97ac6d8d2dc42db4b32fd0042a333802987a7270","isMergeCommit":false,"messageTitle":"Add Some Constraint for Email, Location, and Phone Number","messageBody":"","fileTypesAndContributionMap":{"functional-code":{"insertions":7,"deletions":5},"docs":{"insertions":8,"deletions":1},"test-code":{"insertions":10,"deletions":0}}},{"hash":"27b52aa10dd207ec463adf0848091a9b49ccbde8","isMergeCommit":false,"messageTitle":"Add PPP","messageBody":"","fileTypesAndContributionMap":{"other":{"insertions":1,"deletions":1},"docs":{"insertions":31,"deletions":10}}},{"hash":"66d1edfd4043fdbd53075a333565850a0de4192d","isMergeCommit":true,"messageTitle":"Merge branch \u0027master\u0027 into Fix-Bug","messageBody":"","fileTypesAndContributionMap":{}},{"hash":"d3f2fda0459dcc559b20cc36e29499ff045161e6","isMergeCommit":false,"messageTitle":"Fixing Typo","messageBody":"","fileTypesAndContributionMap":{"functional-code":{"insertions":1,"deletions":1},"test-code":{"insertions":1,"deletions":1}}},{"hash":"ae16ffe8491209e3c801d2ef06d8b4aeaae7f8a7","isMergeCommit":true,"messageTitle":"Merge branch \u0027Fix-Bug\u0027 of https://github.com/angkyakdifp/tp into Fix-Bug","messageBody":"","fileTypesAndContributionMap":{}},{"hash":"e11dffd21b52708e3b0b25044b80278e67b37f44","isMergeCommit":false,"messageTitle":"Fix CheckStyle","messageBody":"","fileTypesAndContributionMap":{"test-code":{"insertions":2,"deletions":2}}}]},{"date":"2023-11-09","commitResults":[{"hash":"5b8679cad7533c02ff40c9b3adfaf14467ce80ae","isMergeCommit":false,"messageTitle":"Fix TYPO","messageBody":"","fileTypesAndContributionMap":{"functional-code":{"insertions":1,"deletions":1}}}]}],"alvinlim277":[{"date":"2023-09-25","commitResults":[{"hash":"b4f38f944a87a0e991fd89db6f0305cfaba86816","isMergeCommit":true,"messageTitle":"Merge pull request #17 from Gavino3o/documentation-11-UpdateAboutUs","messageBody":"Update AboutUs.md and add skeletal PPP","fileTypesAndContributionMap":{}},{"hash":"698cab997809f404530e4cf3d054786767e9f710","isMergeCommit":false,"messageTitle":"Update README.md","messageBody":"","fileTypesAndContributionMap":{"docs":{"insertions":6,"deletions":9}}},{"hash":"50e1abc2d48d9ec2cf3ef96bbaa5a4656c7ae150","isMergeCommit":true,"messageTitle":"Merge branch \u0027master\u0027 into documentation-19-UpdateReadMe","messageBody":"","fileTypesAndContributionMap":{}},{"hash":"b56c54ec5cd7388c3d1ebba4cf45e338371c9c97","isMergeCommit":false,"messageTitle":"Update AboutUs and skeletal PPP","messageBody":"","fileTypesAndContributionMap":{"docs":{"insertions":31,"deletions":4}}},{"hash":"08e86788be5929df9c644a39155428951e4018c9","isMergeCommit":true,"messageTitle":"Merge branch \u0027documentation-19-UpdateReadMe\u0027 into documentation-11-UpdateAboutUs","messageBody":"","fileTypesAndContributionMap":{}},{"hash":"0bd8ab42323122001a69841afd781ee8469944bf","isMergeCommit":false,"messageTitle":"Update GitHub Actions build status badge link","messageBody":"","fileTypesAndContributionMap":{"docs":{"insertions":1,"deletions":1}}},{"hash":"95c21d36962b9c0824351e9b465484e7666064ae","isMergeCommit":true,"messageTitle":"Merge pull request #26 from Kokseng1/documentation-11-UpdateAboutUs","messageBody":"Update AboutUs.md. Add kokseng1.png and kokseng1.md","fileTypesAndContributionMap":{}}]},{"date":"2023-09-26","commitResults":[{"hash":"b7b9646eb626dd3b2b6af8d6fca3031bfaec3351","isMergeCommit":false,"messageTitle":"Update \u0027add\u0027 command in UserGuide.md","messageBody":"","fileTypesAndContributionMap":{"docs":{"insertions":9,"deletions":7}}}]},{"date":"2023-09-27","commitResults":[{"hash":"47a60ff93f00c381d192557f753cc7026506d130","isMergeCommit":false,"messageTitle":"Add command summary for \u0027add\u0027 command","messageBody":"","fileTypesAndContributionMap":{"docs":{"insertions":2,"deletions":1}}},{"hash":"3a3d1529ca44089414c7b91b46aa0812546042b1","isMergeCommit":false,"messageTitle":"Add \u0027exit program\u0027 use case in Developer Guide","messageBody":"","fileTypesAndContributionMap":{"docs":{"insertions":10,"deletions":0}}},{"hash":"bdf440da327ccbe277db543bf67fa6e01e456978","isMergeCommit":false,"messageTitle":"Update \u0027exit program\u0027 use case in Developer Guide","messageBody":"","fileTypesAndContributionMap":{"docs":{"insertions":10,"deletions":3}}}]},{"date":"2023-09-28","commitResults":[{"hash":"bfaed00304abf2661894b5f0060f7716e60a85a6","isMergeCommit":false,"messageTitle":"Fix \u0027exit program\u0027 use case in Developer Guide","messageBody":"","fileTypesAndContributionMap":{"docs":{"insertions":1,"deletions":1}}},{"hash":"c37db398ccfa44946ddf3969977f7ca4cbe6a19e","isMergeCommit":true,"messageTitle":"Merge pull request #40 from Kokseng1/documentation-34-updateDeveloperGuide","messageBody":"Add \u0027add a patient\u0027 use case in DeveloperGuide.md","fileTypesAndContributionMap":{}},{"hash":"dfa5c91cd5189aba1e10ebbbc93ba64112359b9d","isMergeCommit":true,"messageTitle":"Merge pull request #41 from Gavino3o/documentation-34-ListUseCase","messageBody":"Add list command use case in DeveloperGuide.md","fileTypesAndContributionMap":{}},{"hash":"4125393661cf77a67079de9503b13bbaac416396","isMergeCommit":true,"messageTitle":"Merge branch \u0027master\u0027 into documentation-34-UpdateDeveloperGuide","messageBody":"","fileTypesAndContributionMap":{}}]},{"date":"2023-09-29","commitResults":[{"hash":"1350bea0bace71f87542446a45331e3f41bef9ed","isMergeCommit":true,"messageTitle":"Merge pull request #43 from vansh284/documentation-34-UserStories","messageBody":"Add some user stories in dev guide","fileTypesAndContributionMap":{}}]},{"date":"2023-10-02","commitResults":[{"hash":"c450e63ef751935f90344d133aea158ad6103ce4","isMergeCommit":true,"messageTitle":"Merge pull request #45 from Kokseng1/documentation-34-updateDeveloperGuide","messageBody":"update DeveloperGuide to include patient management user stories","fileTypesAndContributionMap":{}},{"hash":"b17ca9ebf59f10560920c3417d319bd02ca813d3","isMergeCommit":false,"messageTitle":"Add data management User Stories to Developer Guide","messageBody":"","fileTypesAndContributionMap":{"docs":{"insertions":24,"deletions":19}}}]},{"date":"2023-10-03","commitResults":[{"hash":"2f2e29de3d8105f054783533233ff77cda22dc1c","isMergeCommit":false,"messageTitle":"Add Ui mockup to README","messageBody":"","fileTypesAndContributionMap":{"docs":{"insertions":1,"deletions":1}}}]},{"date":"2023-10-05","commitResults":[{"hash":"82b1dd24fe2dce03dc3628dde205b169d223380a","isMergeCommit":true,"messageTitle":"Merge pull request #52 from angkyakdifp/branch-user-guide","messageBody":"Add Specialist Management User Guide","fileTypesAndContributionMap":{}},{"hash":"34bfdc830fa98c4469cb710a24bc4abf458b03d8","isMergeCommit":false,"messageTitle":"Update _config.yml","messageBody":"","fileTypesAndContributionMap":{"docs":{"insertions":2,"deletions":2}}}]},{"date":"2023-10-12","commitResults":[{"hash":"8713685321720f101fec03fef699b9315936c339","isMergeCommit":false,"messageTitle":"Update ListCommand","messageBody":"","fileTypesAndContributionMap":{"functional-code":{"insertions":36,"deletions":6},"test-code":{"insertions":4,"deletions":3}}},{"hash":"befbb5cb7fd41e24231290b6fc63d5bd4b26f30f","isMergeCommit":false,"messageTitle":"Update PersonType enum and change DeleteCommand","messageBody":"DeleteCommand now executes based on the last/currently\ndisplayed list and is unaffected by personType tags.\n","fileTypesAndContributionMap":{"functional-code":{"insertions":26,"deletions":20},"test-code":{"insertions":24,"deletions":22}}},{"hash":"9a809a90b64a72525838de9ddd5bb5accbfda1b3","isMergeCommit":false,"messageTitle":"Fix test failures related to EditCommand","messageBody":"Changes made to the ModelManager class resulted in testcase\nfailures. This commit rectifies them by editing the EditCommand\nclass to update the filtered list appropriately in the model on\nexecution.\n","fileTypesAndContributionMap":{"functional-code":{"insertions":10,"deletions":13},"test-code":{"insertions":26,"deletions":25}}},{"hash":"9cf91f1866a9ab07cf5921063413761a70430d88","isMergeCommit":false,"messageTitle":"Fix checkstyle issues","messageBody":"","fileTypesAndContributionMap":{"functional-code":{"insertions":0,"deletions":2}}},{"hash":"921f43ca2aea65ca7c5cb8ad0ddbd5df5bd5fde4","isMergeCommit":false,"messageTitle":"Fix checkstyle issues","messageBody":"","fileTypesAndContributionMap":{"test-code":{"insertions":0,"deletions":3}}},{"hash":"3141d9d0cb8670d7c00ad7753a9b63c816489a6e","isMergeCommit":false,"messageTitle":"Improve code coverage","messageBody":"","fileTypesAndContributionMap":{"functional-code":{"insertions":2,"deletions":1},"test-code":{"insertions":12,"deletions":4}}}]},{"date":"2023-10-13","commitResults":[{"hash":"fdb461e50f8c8732cb27f77a85264a9870a30241","isMergeCommit":false,"messageTitle":"Rectify Edit and Delete implementation","messageBody":"EditCommand was erroneously edited to take personType as a parameter\nin the previous commits. Its syntax and implementation remain an issue,\nbut the errors have been undone at surface level for now.\n\nDeleteCommand was being parsed with a personType, which is unused in\nimplementation. To resolve this, ParserBasic and ParserComplex classes\nhave been written to better suit the needs as well as aid in testing.\n- Basic commands do not require specifying personType\n- Complex commands require a personType tag\nIt is very likely that we will add more basic commands in the future as\nwell, for example changing user settings, exporting data etc.\n\nAlso fix some bugs with the parsing of different command Patterns\n- Previously Basic commands could also be parsed as Complex\n- This has been fixed by altering the Complex command regex to be more\nrestrictive.\n","fileTypesAndContributionMap":{"functional-code":{"insertions":34,"deletions":26},"other":{"insertions":2,"deletions":2},"docs":{"insertions":5,"deletions":5},"test-code":{"insertions":139,"deletions":116}}}]},{"date":"2023-10-16","commitResults":[{"hash":"3ddf917bbb0d44f7214d6b0ce950a4b85b01dbb2","isMergeCommit":true,"messageTitle":"Merge pull request #66 from Gavino3o/feature-10-FindByPrefix","messageBody":"Implement FindCommand to search using prefixes","fileTypesAndContributionMap":{}},{"hash":"a4d0fa75ef7164f674db8d2d57fe9c5be2baadea","isMergeCommit":false,"messageTitle":"Change Address to Location","messageBody":"","fileTypesAndContributionMap":{"functional-code":{"insertions":117,"deletions":113},"other":{"insertions":16,"deletions":16},"test-code":{"insertions":186,"deletions":186}}},{"hash":"49d8cf7d3f81060cf877d751960cb72b66aadb92","isMergeCommit":false,"messageTitle":"Start making Location exclusive to Specialists","messageBody":"","fileTypesAndContributionMap":{"functional-code":{"insertions":66,"deletions":78},"other":{"insertions":14,"deletions":7},"test-code":{"insertions":97,"deletions":131}}},{"hash":"1788e7d84fcb4334ae585c137c60bf95ef4d630d","isMergeCommit":false,"messageTitle":"Fix AddCommand bug and checkstyle issues","messageBody":"","fileTypesAndContributionMap":{"functional-code":{"insertions":8,"deletions":1},"test-code":{"insertions":47,"deletions":24}}},{"hash":"af3dc9d922bcf989f21e3532705253bb035b2c6d","isMergeCommit":false,"messageTitle":"Fix command help messages","messageBody":"","fileTypesAndContributionMap":{"functional-code":{"insertions":3,"deletions":3}}},{"hash":"71fc7db77c0f3cb6fee866930ec2e5b5bd9063f7","isMergeCommit":false,"messageTitle":"Improve code coverage","messageBody":"","fileTypesAndContributionMap":{"test-code":{"insertions":26,"deletions":2}}},{"hash":"8f7e8284ee311cdb08b91f0bb70a884119ef802d","isMergeCommit":true,"messageTitle":"Fix merge conflicts","messageBody":"","fileTypesAndContributionMap":{}},{"hash":"4d43ece44087706b2c4bba07d2be95b4d8430061","isMergeCommit":false,"messageTitle":"Fix minor errors","messageBody":"","fileTypesAndContributionMap":{"test-code":{"insertions":7,"deletions":2}}}]},{"date":"2023-10-23","commitResults":[{"hash":"e9a9416d447364186d07952c3dc45812ca2915a6","isMergeCommit":false,"messageTitle":"Improve find command flexibility","messageBody":"Change find command so that it does a substring search for\ncertain parameters that are inconvenient to query by whole words.\n\nSpecifically:\n- Name (Searching by short forms of long names)\n- Email (Searching for emails without having to type out domain\nnames)\n- Location (Searching for long addresses made easier)\n- Phone (Searching for people by phone possible even if the\nwhole phone number is not memorised)\n","fileTypesAndContributionMap":{"functional-code":{"insertions":29,"deletions":4},"docs":{"insertions":18,"deletions":11},"test-code":{"insertions":71,"deletions":0}}},{"hash":"a27a4cec4387103216e00e58be4685f36a057cf7","isMergeCommit":false,"messageTitle":"Fix usage message error","messageBody":"","fileTypesAndContributionMap":{"functional-code":{"insertions":6,"deletions":6}}},{"hash":"917ca1d9259f495af08abb3646c1b99b430fa65f","isMergeCommit":false,"messageTitle":"Fix testing and checkstyle errors","messageBody":"","fileTypesAndContributionMap":{"functional-code":{"insertions":2,"deletions":1},"test-code":{"insertions":18,"deletions":11}}}]},{"date":"2023-10-24","commitResults":[{"hash":"dc4d32fdcf75549a2b51013718da616d9f698716","isMergeCommit":false,"messageTitle":"Update substring search behaviour","messageBody":"","fileTypesAndContributionMap":{"functional-code":{"insertions":3,"deletions":2},"docs":{"insertions":6,"deletions":6}}},{"hash":"b08cfd16e8e325fcf9b4754755b0cb3148de505f","isMergeCommit":true,"messageTitle":"Merge pull request #88 from alvinlim277/enhancement-87-FindCommand","messageBody":"Improve find command flexibility","fileTypesAndContributionMap":{}},{"hash":"1995ca4eabab74fb973d3ffcb93c95a4ab978fe7","isMergeCommit":false,"messageTitle":"Add ShortcutSettings to UserPrefs","messageBody":"","fileTypesAndContributionMap":{"functional-code":{"insertions":166,"deletions":5},"test-code":{"insertions":2,"deletions":1}}}]},{"date":"2023-10-25","commitResults":[{"hash":"72158dc23257047930013072b9a49f7cfbad7973","isMergeCommit":false,"messageTitle":"Add add shortcut command","messageBody":"","fileTypesAndContributionMap":{"functional-code":{"insertions":107,"deletions":7},"test-code":{"insertions":2,"deletions":1}}},{"hash":"229df810fd8a16fec0d678d2f836a79a535f8d29","isMergeCommit":false,"messageTitle":"Improve design correctness","messageBody":"","fileTypesAndContributionMap":{"functional-code":{"insertions":3,"deletions":36}}},{"hash":"7292807ea2e08f0f024abe27fe24e25cfea8b2b2","isMergeCommit":false,"messageTitle":"Add wrapper classes and constraints","messageBody":"","fileTypesAndContributionMap":{"functional-code":{"insertions":208,"deletions":34}}},{"hash":"1fca640dab4c569ded1226a978c5be1c421edacf","isMergeCommit":false,"messageTitle":"Add delete shortcut function","messageBody":"","fileTypesAndContributionMap":{"functional-code":{"insertions":111,"deletions":7}}},{"hash":"3cf6272a79a866603978823cb16b081a3935e00f","isMergeCommit":false,"messageTitle":"Update UserGuide and add some testing","messageBody":"","fileTypesAndContributionMap":{"functional-code":{"insertions":47,"deletions":1},"docs":{"insertions":24,"deletions":0},"test-code":{"insertions":151,"deletions":0}}},{"hash":"90d2762dcd6a8a246a48b99878cb281412e5fd62","isMergeCommit":false,"messageTitle":"Improve test coverage","messageBody":"","fileTypesAndContributionMap":{"functional-code":{"insertions":60,"deletions":30},"test-code":{"insertions":290,"deletions":9}}},{"hash":"e2d6cb7892b7f52d7f512b1109117507bcfd8de9","isMergeCommit":false,"messageTitle":"Fix checkstyle issues","messageBody":"","fileTypesAndContributionMap":{"functional-code":{"insertions":29,"deletions":20},"test-code":{"insertions":38,"deletions":37}}},{"hash":"23a214a94606597dd626c38e78b3d234e855e43f","isMergeCommit":true,"messageTitle":"Merge branch \u0027master\u0027 into story-9-Shortcuts","messageBody":"","fileTypesAndContributionMap":{}},{"hash":"63556476cef2b0dae0b159a1a975c57c2d6e3d66","isMergeCommit":false,"messageTitle":"Fix checkstyle issues","messageBody":"","fileTypesAndContributionMap":{"functional-code":{"insertions":1,"deletions":1}}},{"hash":"8e7553e5f9931f887a8bf4ceffd18df6eac5fea1","isMergeCommit":false,"messageTitle":"Fix bad mapping bug","messageBody":"","fileTypesAndContributionMap":{"functional-code":{"insertions":26,"deletions":3}}},{"hash":"dee4ae9cf2a3b80b9cc352e6cd37baac7396a5f8","isMergeCommit":false,"messageTitle":"Fix checkstyle issues","messageBody":"","fileTypesAndContributionMap":{"functional-code":{"insertions":0,"deletions":1}}}]},{"date":"2023-10-26","commitResults":[{"hash":"8894dfbfdf3fbfb1d2b84cb9ec7e660ffce33726","isMergeCommit":false,"messageTitle":"Fix minor bugs","messageBody":"","fileTypesAndContributionMap":{"functional-code":{"insertions":11,"deletions":20},"docs":{"insertions":1,"deletions":1}}},{"hash":"46f0bbc03903126ab1bc267914043d14ed80b973","isMergeCommit":true,"messageTitle":"Merge branch \u0027master\u0027 into story-9-Shortcuts","messageBody":"","fileTypesAndContributionMap":{}},{"hash":"d8230a9e16e5a28af5fe93db7708f4470b5a1ab7","isMergeCommit":false,"messageTitle":"Fix FindCommand bug","messageBody":"","fileTypesAndContributionMap":{"functional-code":{"insertions":21,"deletions":2}}},{"hash":"11c310391263b2abbc79f2527b3f8cabe3ede0dc","isMergeCommit":false,"messageTitle":"Fix JavaDoc header","messageBody":"","fileTypesAndContributionMap":{"functional-code":{"insertions":2,"deletions":2}}},{"hash":"bb5af920822275cf9bf3298d54270eaf0acd260c","isMergeCommit":false,"messageTitle":"Amend UserGuide","messageBody":"","fileTypesAndContributionMap":{"docs":{"insertions":3,"deletions":1}}},{"hash":"a6c5d96d55c82462c2b6b05dd7e00328d8678172","isMergeCommit":true,"messageTitle":"Merge branch \u0027master\u0027 into story-9-Shortcuts","messageBody":"","fileTypesAndContributionMap":{}},{"hash":"df8d82835818f6f2cb8c3ef9ede8fab243af94aa","isMergeCommit":true,"messageTitle":"Merge pull request #93 from alvinlim277/story-9-Shortcuts","messageBody":"Add shortcuts feature","fileTypesAndContributionMap":{}},{"hash":"9ae27f3f3a7b791618b36b00ca93dd60cd9e05e5","isMergeCommit":true,"messageTitle":"Merge pull request #96 from vansh284/enhancement-improveRecentCommandCode","messageBody":"Update developer guide for Recall Recent Commands","fileTypesAndContributionMap":{}},{"hash":"dacec3c941da6b6d81c3c9cbea616b95477a77da","isMergeCommit":false,"messageTitle":"Correct LoD violation and start on DG","messageBody":"","fileTypesAndContributionMap":{"functional-code":{"insertions":41,"deletions":6},"docs":{"insertions":25,"deletions":0}}},{"hash":"dec5845c49451827aa7784c01644c3d2b863deb3","isMergeCommit":false,"messageTitle":"Update Developer Guide","messageBody":"","fileTypesAndContributionMap":{"functional-code":{"insertions":1,"deletions":1},"docs":{"insertions":119,"deletions":5}}},{"hash":"5915e00adf32fc293a367e937f1c85f468c0ed28","isMergeCommit":false,"messageTitle":"Update Developer Guide draft","messageBody":"","fileTypesAndContributionMap":{"docs":{"insertions":78,"deletions":23}}},{"hash":"5620ea33e1e2e277a1e716bcc68d7b528e9bc256","isMergeCommit":false,"messageTitle":"Fix checkstyle and test bugs","messageBody":"","fileTypesAndContributionMap":{"functional-code":{"insertions":0,"deletions":6},"test-code":{"insertions":15,"deletions":0}}},{"hash":"e1dae54be5e96274c73a1959874a2ce4614f9ece","isMergeCommit":false,"messageTitle":"Fix duplicate shortcut message error","messageBody":"","fileTypesAndContributionMap":{"functional-code":{"insertions":6,"deletions":0},"test-code":{"insertions":20,"deletions":1}}},{"hash":"4a2b65beeca31908a49c8e36f72f26eda008916a","isMergeCommit":false,"messageTitle":"Fix repo test errors","messageBody":"","fileTypesAndContributionMap":{"docs":{"insertions":8,"deletions":8}}},{"hash":"b5d21ff0d73e986858150bd7a526de1fa138a2cb","isMergeCommit":false,"messageTitle":"Amend activity diagrams","messageBody":"","fileTypesAndContributionMap":{"docs":{"insertions":3,"deletions":6}}}]},{"date":"2023-10-27","commitResults":[{"hash":"be11c23aebe5eb1325d3f13755cde75c35f07086","isMergeCommit":false,"messageTitle":"Amend UML diagrams","messageBody":"","fileTypesAndContributionMap":{"docs":{"insertions":5,"deletions":5}}},{"hash":"8c4e73f5be86d81e2b970018cf0bf3f8cb1e8fc7","isMergeCommit":true,"messageTitle":"Merge pull request #102 from angkyakdifp/branch-Documentation-DG","messageBody":"Improve Developer Guide","fileTypesAndContributionMap":{}}]},{"date":"2023-10-29","commitResults":[{"hash":"4b2ad95fe7f4441fbd805d8fd5efbfadfad5469c","isMergeCommit":false,"messageTitle":"Resolve duplicate person bug","messageBody":"","fileTypesAndContributionMap":{"functional-code":{"insertions":26,"deletions":0},"test-code":{"insertions":47,"deletions":4}}},{"hash":"d6c696ca2861404851506fbfef89f8bbeb2e91da","isMergeCommit":false,"messageTitle":"Improve code coverage","messageBody":"","fileTypesAndContributionMap":{"functional-code":{"insertions":9,"deletions":12}}},{"hash":"4150eee0a440cd9e669c4c532d9336d370f3fc2b","isMergeCommit":true,"messageTitle":"Merge pull request #112 from vansh284/bugfix-101-duplicateRecallCommand","messageBody":"Handle duplicate commands properly when recalling commands","fileTypesAndContributionMap":{}},{"hash":"6be660d4137dccd70ebcaffcb9cd82e682ef79a1","isMergeCommit":false,"messageTitle":"Fix PersonTypeBar bugs","messageBody":"Added a `NO DATA` label to get around the case where the filtered\npersons list is empty without needing to know what the user is\ntrying to view.\n\nChanged how the PersonTypeBar is updated so mouse clicks are\nunecessary.\n","fileTypesAndContributionMap":{"functional-code":{"insertions":41,"deletions":6}}},{"hash":"4adc7adf3bdc5238e4d5e7ea511394a2ca7fa94d","isMergeCommit":true,"messageTitle":"Merge branch \u0027master\u0027 into bugfix-109-PersonTypeBar","messageBody":"","fileTypesAndContributionMap":{}},{"hash":"72aab66ff879545f968489eae6c0b3a1c2e94733","isMergeCommit":false,"messageTitle":"Update UserGuide","messageBody":"","fileTypesAndContributionMap":{"functional-code":{"insertions":6,"deletions":6},"docs":{"insertions":13,"deletions":0}}},{"hash":"f7bd68f7eddb81fd66d3e72dde25cb5c3a2bd7c7","isMergeCommit":true,"messageTitle":"Merge pull request #105 from Gavino3o/feature-63-ModifyEditCommandBehavior","messageBody":"Modify Edit Command to align with View Command","fileTypesAndContributionMap":{}}]},{"date":"2023-10-31","commitResults":[{"hash":"30bf4c86634e04b81ae7f2689a6302cee8c8efe8","isMergeCommit":true,"messageTitle":"Merge branch \u0027master\u0027 into bugfix-109-PersonTypeBar","messageBody":"","fileTypesAndContributionMap":{}}]},{"date":"2023-11-02","commitResults":[{"hash":"497399421635b9a7e7a6fa919ae4058d42e1a113","isMergeCommit":true,"messageTitle":"Merge pull request #118 from Gavino3o/documentation-97-UGUpdates","messageBody":"Minor UG Updates","fileTypesAndContributionMap":{}}]},{"date":"2023-11-07","commitResults":[{"hash":"dafc31212aa0058721cca38cd1cc0cb95b6b4698","isMergeCommit":false,"messageTitle":"Fix bugs for v1.4","messageBody":"Fix various bugs while updating documentation and PPP.\n","fileTypesAndContributionMap":{"functional-code":{"insertions":6,"deletions":4},"docs":{"insertions":32,"deletions":9}}},{"hash":"730a63108efbb3dcf4961f2a7fa7dbb5051e67b2","isMergeCommit":false,"messageTitle":"Fix checkstyle and credit reuse","messageBody":"","fileTypesAndContributionMap":{"functional-code":{"insertions":3,"deletions":3},"docs":{"insertions":3,"deletions":3}}},{"hash":"db7fdf36b93be69f313d3717543ea81f08b0a2f1","isMergeCommit":true,"messageTitle":"Merge branch \u0027master\u0027 into bugfixes-v1.4","messageBody":"","fileTypesAndContributionMap":{}}]},{"date":"2023-11-08","commitResults":[{"hash":"56e92891c7ebaf8740e8660a1447bce892b620d0","isMergeCommit":true,"messageTitle":"Merge branch \u0027master\u0027 into bugfixes-v1.4","messageBody":"","fileTypesAndContributionMap":{}},{"hash":"bdb1d20c9f1c18212d7859b723a4064289f17fc6","isMergeCommit":false,"messageTitle":"Update Developer Guide","messageBody":"","fileTypesAndContributionMap":{"docs":{"insertions":3,"deletions":3}}},{"hash":"760595f3339892165f74235a3a5fe60caebf2d7e","isMergeCommit":true,"messageTitle":"Merge branch \u0027master\u0027 into bugfixes-v1.4","messageBody":"","fileTypesAndContributionMap":{}},{"hash":"e6a0ccdbbcdc8df4a80d0bdaa2722ca286ead0be","isMergeCommit":true,"messageTitle":"Merge branch \u0027bugfixes-v1.4\u0027 of https://github.com/alvinlim277/tp into bugfixes-v1.4","messageBody":"","fileTypesAndContributionMap":{}},{"hash":"0c2c94622f68e4dd8f17d1027583528236c1740c","isMergeCommit":false,"messageTitle":"Remove extra whitespace","messageBody":"","fileTypesAndContributionMap":{"docs":{"insertions":1,"deletions":1}}}]},{"date":"2023-11-10","commitResults":[{"hash":"ab89f51a8c9b7029ba7b0646a355c3d531b2c1ee","isMergeCommit":false,"messageTitle":"Clarify delsc behaviour in UserGuide","messageBody":"Also changed error message for DeleteShortcutCommand.\nFixes #163\n","fileTypesAndContributionMap":{"functional-code":{"insertions":1,"deletions":1},"docs":{"insertions":13,"deletions":2}}},{"hash":"2c3974dabd6652ea30407b4e149455cfc3610529","isMergeCommit":false,"messageTitle":"Fix wording in UG","messageBody":"","fileTypesAndContributionMap":{"docs":{"insertions":2,"deletions":2}}}]},{"date":"2023-11-12","commitResults":[{"hash":"ae92d7043fe3bf403f094c16247fc89cef4958d6","isMergeCommit":false,"messageTitle":"Fix documentation","messageBody":"","fileTypesAndContributionMap":{"docs":{"insertions":16,"deletions":13}}},{"hash":"5da981ab6f57db05f7d97c8e4e5a639f4a85fed2","isMergeCommit":true,"messageTitle":"Merge branch \u0027master\u0027 into documentation-fixes","messageBody":"","fileTypesAndContributionMap":{}},{"hash":"26d3bb1c4fbec03cb42aefbd8150d4b6a99322c7","isMergeCommit":false,"messageTitle":"Edit documentation","messageBody":"","fileTypesAndContributionMap":{"functional-code":{"insertions":3,"deletions":3},"docs":{"insertions":17,"deletions":11}}},{"hash":"90faab61a8e9f8d97eda98ec72d7c7edf160f84b","isMergeCommit":false,"messageTitle":"Fix some typos","messageBody":"","fileTypesAndContributionMap":{"docs":{"insertions":5,"deletions":5}}},{"hash":"72a0b94ab16790fdbfa959ef3aa41e14e2dc2390","isMergeCommit":false,"messageTitle":"Update planned enhancements","messageBody":"Fixes #174\n","fileTypesAndContributionMap":{"docs":{"insertions":9,"deletions":2}}},{"hash":"5469b3e23438758f0366b9378ef3856b12055891","isMergeCommit":false,"messageTitle":"Edit documentation","messageBody":"","fileTypesAndContributionMap":{"docs":{"insertions":1,"deletions":5}}},{"hash":"1da7b46dd6f5c95ccf6b1c73ff4c29927b94042c","isMergeCommit":false,"messageTitle":"Add newlines","messageBody":"","fileTypesAndContributionMap":{"docs":{"insertions":2,"deletions":2}}},{"hash":"7f66f64f11875df54f18d3fdfb27a651f05b565b","isMergeCommit":true,"messageTitle":"Merge pull request #178 from vansh284/documentation-moreFixes","messageBody":"Documentation more fixes","fileTypesAndContributionMap":{}},{"hash":"0bd8e3fc736583dba1c60abbb562db208f6a7300","isMergeCommit":true,"messageTitle":"Merge pull request #179 from Kokseng1/bugfix-documentation","messageBody":"Bugfix documentation","fileTypesAndContributionMap":{}}]}]},"authorFileTypeContributionMap":{"Kokseng1":{"docs":115,"functional-code":643,"test-code":662},"vansh284":{"docs":560,"functional-code":1535,"test-code":933,"other":2},"Gavino3o":{"docs":429,"functional-code":602,"test-code":677},"angkyakdifp":{"docs":243,"functional-code":816,"test-code":495,"other":1},"alvinlim277":{"docs":342,"functional-code":975,"test-code":926}},"authorContributionVariance":{"Kokseng1":39412.29,"vansh284":111777.34,"Gavino3o":17912.867,"angkyakdifp":26723.996,"alvinlim277":59304.81},"authorDisplayNameMap":{"Kokseng1":"CS2103T-W13-1 NG K..SENG","vansh284":"CS2103T-W13-1 VANS..NATH","Gavino3o":"CS2103T-W13-1 GAVI.. ZHE","angkyakdifp":"CS2103T-W13-1 ANGK..LANA","alvinlim277":"CS2103T-W13-1 LIM ..LVIN"}}
